[{"username":"fgeorgeson0","password":"QACp4LuOY","email":"maspden0@usatoday.com"},
{"username":"inanetti1","password":"123qwe","email":"hglassard1@wisc.edu"},
{"username":"atutchener2","password":"jEvaXXcX","email":"wspenton2@behance.net"},
{"username":"sbatey3","password":"7ZSQIN","email":"efenelon3@rediff.com"},
{"username":"awitchard4","password":"b9wQWYfa","email":"lzebedee4@histats.com"},
{"username":"mipsgrave5","password":"0NFpdWc","email":"cheister5@behance.net"},
{"username":"mbindon6","password":"EKCv7ptp4","email":"cdelboux6@furl.net"},
{"username":"bech7","password":"5hGsqvx0","email":"cocurneen7@cafepress.com"},
{"username":"lhugonneau8","password":"Qz6ttzvn","email":"tmaccartney8@cmu.edu"},
{"username":"clangland9","password":"KjRDPa","email":"omcdonogh9@feedburner.com"},
{"username":"gbielfelda","password":"FIRYocrOyw","email":"vavrahamya@cnet.com"},
{"username":"mjouenb","password":"TOZdut","email":"scutmoreb@tripod.com"},
{"username":"rduffanc","password":"XurRUg4IRAQ","email":"bagronc@phpbb.com"},
{"username":"eandoverd","password":"AQzRs7","email":"epensond@disqus.com"},
{"username":"styrwhitte","password":"7aeJJz2kBDJ","email":"khaskinse@slideshare.net"},
{"username":"awoodyattf","password":"WBXeQKKlSSZd","email":"ebrasseurf@netlog.com"},
{"username":"gbartoshevichg","password":"xk94rR","email":"wmeliorg@google.co.uk"},
{"username":"etraiseh","password":"TdUMs08","email":"wmcgavinh@livejournal.com"},
{"username":"cbertrami","password":"IoYipv0bm","email":"respineli@tumblr.com"},
{"username":"sjacobbej","password":"0jE8oA4425Mv","email":"tfiskej@google.it"},
{"username":"dhatherleyk","password":"XvfCqlBXI","email":"srelfk@comsenz.com"},
{"username":"acloutel","password":"vKnCNeagwU6","email":"dmytonl@archive.org"},
{"username":"aswainsonm","password":"MWqK8xx2","email":"cgawkesm@topsy.com"},
{"username":"eleckien","password":"39NxeMDkg","email":"idouchen@senate.gov"},
{"username":"nquicko","password":"yDCx3KBWJ","email":"hjanuso@dion.ne.jp"},
{"username":"kbachsp","password":"yguar8BEN","email":"cdrewep@rakuten.co.jp"},
{"username":"blearoidq","password":"S95zLED","email":"cmccaullq@baidu.com"},
{"username":"durpethr","password":"uu0ojvb5","email":"growlattr@xing.com"},
{"username":"cshankles","password":"XhQ9xVwZ","email":"hellamss@dagondesign.com"},
{"username":"eframet","password":"IB6Uu8LIGN","email":"bmacveyt@umn.edu"},
{"username":"mcopleyu","password":"bE3b9nGzome","email":"smarslandu@plala.or.jp"},
{"username":"rdukesburyv","password":"bFiDXxJKLR","email":"nbusekv@boston.com"},
{"username":"matwoolw","password":"wHDCdFetPP","email":"cgrzegorzewiczw@deviantart.com"},
{"username":"jkleesx","password":"WLu8mKfZCqj","email":"respinolax@columbia.edu"},
{"username":"speatheyjohnsy","password":"XGvjCmb","email":"rvanichkiny@auda.org.au"},
{"username":"cjaslemz","password":"xQZcBC4PBfH","email":"malabastarz@archive.org"},
{"username":"jdupoy10","password":"tjwKDJDvE","email":"sscotson10@slideshare.net"},
{"username":"eacarson11","password":"3mzmgobJ","email":"nperes11@ox.ac.uk"},
{"username":"abrumfitt12","password":"fDaIPX5","email":"lianno12@g.co"},
{"username":"pniess13","password":"IrDRYsOA4O","email":"rvasyutkin13@senate.gov"},
{"username":"cleonard14","password":"RhJvALAdS1G","email":"otoone14@sciencedaily.com"},
{"username":"dcowern15","password":"nQwhdhvF","email":"wmeus15@woothemes.com"},
{"username":"cmercik16","password":"ZhumB0KrAbS","email":"cpatel16@timesonline.co.uk"},
{"username":"lroger17","password":"iemgEW","email":"ktindle17@stanford.edu"},
{"username":"mavo18","password":"YMRA3tABgr8R","email":"gcroose18@furl.net"},
{"username":"syosevitz19","password":"hXsUKAo","email":"mroullier19@addthis.com"},
{"username":"dmorgen1a","password":"CKNgKE4VY","email":"btummons1a@sciencedirect.com"},
{"username":"zmarusic1b","password":"XUPDb48J1D","email":"dodonegan1b@diigo.com"},
{"username":"rwoolfenden1c","password":"bNybFEyExws","email":"ocrack1c@trellian.com"},
{"username":"jmuckle1d","password":"I29e80K","email":"pwillbourne1d@t-online.de"},
{"username":"dmactrustey1e","password":"aSNYgWjA8XAP","email":"mpablo1e@dailymotion.com"},
{"username":"dgodain1f","password":"sMkpwNx","email":"yfasse1f@economist.com"},
{"username":"hweinberg1g","password":"lYrfjKVruTA","email":"fsimionescu1g@miibeian.gov.cn"},
{"username":"jslimmon1h","password":"5nM0zS9zka","email":"keouzan1h@marriott.com"},
{"username":"tchipchase1i","password":"JflaQ4","email":"btarplee1i@posterous.com"},
{"username":"dhaken1j","password":"3AnhImyy","email":"tbroadnicke1j@chron.com"},
{"username":"gtarply1k","password":"go6yprM","email":"kllorens1k@spotify.com"},
{"username":"ebulfield1l","password":"AH1eBKTuCFrG","email":"asharpley1l@home.pl"},
{"username":"tevetts1m","password":"kKg2vjS1ylLJ","email":"cketteringham1m@gov.uk"},
{"username":"deneas1n","password":"g7C8hYEsNM","email":"gpitkaithly1n@1und1.de"},
{"username":"floudyan1o","password":"h2OIyNTem","email":"ylandsbury1o@thetimes.co.uk"},
{"username":"klejeune1p","password":"XcC8WN2","email":"fbarwack1p@nydailynews.com"},
{"username":"hwarbeys1q","password":"9oghHECIr","email":"cwragge1q@indiatimes.com"},
{"username":"scheccucci1r","password":"PrMjWjx","email":"bfeatherston1r@zimbio.com"},
{"username":"kgoburn1s","password":"RHAen3cVes4u","email":"cjeynes1s@mtv.com"},
{"username":"dday1t","password":"zprL3MmgOF","email":"csowersby1t@cyberchimps.com"},
{"username":"cspurdens1u","password":"i4AHUZ","email":"rcasino1u@jiathis.com"},
{"username":"tsinnatt1v","password":"NFdmSS4t","email":"rambrogi1v@tinyurl.com"},
{"username":"skighly1w","password":"AIkKYBNMDs5o","email":"iglandfield1w@wikipedia.org"},
{"username":"dechlin1x","password":"hvxsBRAnv","email":"rcruise1x@photobucket.com"},
{"username":"cgudd1y","password":"T72m16gp3Qq","email":"jkiendl1y@php.net"},
{"username":"jregelous1z","password":"dnPTUwiEK","email":"cboreham1z@blinklist.com"},
{"username":"tkingsbury20","password":"sT5WtA","email":"rdavids20@ovh.net"},
{"username":"jsexti21","password":"8QpxOuHaD1","email":"jlunnon21@mayoclinic.com"},
{"username":"gvalentetti22","password":"qtkFXwBl","email":"rcordie22@marriott.com"},
{"username":"jmoniker23","password":"SDOfG7JdRofB","email":"dmarlowe23@archive.org"},
{"username":"kcopeland24","password":"8j5JxIG3","email":"rvian24@rakuten.co.jp"},
{"username":"mseaborn25","password":"1J7ynS","email":"crubinchik25@yahoo.co.jp"},
{"username":"rsmithson26","password":"39KHItqiC","email":"ebecket26@yellowbook.com"},
{"username":"melbourne27","password":"TCgBF8B","email":"bmcewan27@eepurl.com"},
{"username":"skleiser28","password":"IciX2IriM","email":"lmelmore28@usgs.gov"},
{"username":"avassbender29","password":"NbTbc2WsXG","email":"jhampshaw29@huffingtonpost.com"},
{"username":"ghanington2a","password":"sGE2hlmj0OX","email":"mgommes2a@sbwire.com"},
{"username":"gschumacher2b","password":"xLRjtqK","email":"kharwin2b@mac.com"},
{"username":"stolan2c","password":"1QfWVA","email":"tturbitt2c@japanpost.jp"},
{"username":"fgilley2d","password":"37Oz4PJQ","email":"kmanger2d@unblog.fr"},
{"username":"schamney2e","password":"SiPIcJYr","email":"sgilfether2e@utexas.edu"},
{"username":"ititford2f","password":"Ryh29C6FqYwN","email":"ebroadnicke2f@pagesperso-orange.fr"},
{"username":"wholtham2g","password":"OJYhCrU1h","email":"fsutherington2g@odnoklassniki.ru"},
{"username":"amonard2h","password":"2amEitA29kv5","email":"gfrowde2h@myspace.com"},
{"username":"dmonsey2i","password":"wOozo52UK","email":"wlamartine2i@npr.org"},
{"username":"dportwain2j","password":"WOMHpTBwJ","email":"idorricott2j@sun.com"},
{"username":"bconaboy2k","password":"z09fJdSRTja","email":"kpollendine2k@yandex.ru"},
{"username":"arichardes2l","password":"aoBUDKjxm","email":"jwheatman2l@liveinternet.ru"},
{"username":"hethridge2m","password":"3g8JaQGsb","email":"mdonegan2m@flavors.me"},
{"username":"rdanielli2n","password":"sVOrWwHl7Ed","email":"rbucknill2n@liveinternet.ru"},
{"username":"emaccawley2o","password":"Z2YhPMyX","email":"adoppler2o@ucoz.com"},
{"username":"ggait2p","password":"wu18gshay","email":"hhebbron2p@delicious.com"},
{"username":"gpizey2q","password":"0wqXDi","email":"tgouldbourn2q@upenn.edu"},
{"username":"sissett2r","password":"itxjcK","email":"pchoat2r@gnu.org"},
{"username":"uredsull2s","password":"DKAjwAl6dt","email":"reagan2s@wired.com"},
{"username":"cbelf2t","password":"zEoe7i","email":"wmartinho2t@europa.eu"},
{"username":"abresnen2u","password":"UnROEXDR","email":"bmccosker2u@mail.ru"},
{"username":"jmeere2v","password":"Va5fpuM","email":"browlett2v@list-manage.com"},
{"username":"grobbie2w","password":"uurfUv","email":"vmorpeth2w@samsung.com"},
{"username":"whitzke2x","password":"GMaBM4SDrf9","email":"tbeckey2x@spiegel.de"},
{"username":"jdevaar2y","password":"sAzFOVV","email":"trounding2y@sogou.com"},
{"username":"estirman2z","password":"9kVcoiZYaD8N","email":"mdjordjevic2z@amazon.de"},
{"username":"clovewell30","password":"r9uFpOTbwI","email":"fcollerd30@mac.com"},
{"username":"tmarjoram31","password":"iCdXO3OLQD","email":"lneighbour31@multiply.com"},
{"username":"bperrone32","password":"CTvgfOAkNhHA","email":"bmcfetrich32@mapy.cz"},
{"username":"glightwood33","password":"voMAo7","email":"swithnall33@a8.net"},
{"username":"kchallenor34","password":"09a4vhS","email":"sgreaterex34@tripadvisor.com"},
{"username":"sturbefield35","password":"T2B0vqs","email":"cberthot35@slashdot.org"},
{"username":"nbridgman36","password":"CwjKUBBS0","email":"ggottelier36@reference.com"},
{"username":"hcreany37","password":"QPl4j4","email":"greasce37@boston.com"},
{"username":"lrainger38","password":"h7mGCkhNE0X","email":"elawlan38@washington.edu"},
{"username":"crathe39","password":"qHOafao2TxV","email":"tdunkley39@cbsnews.com"},
{"username":"fflatley3a","password":"vItGyDmhURr","email":"bleblanc3a@unesco.org"},
{"username":"bdimberline3b","password":"22XvSYQx","email":"kbelsey3b@istockphoto.com"},
{"username":"clye3c","password":"JK8r0ftEbk","email":"blangelaan3c@fastcompany.com"},
{"username":"bsea3d","password":"um2hBYmG4xs","email":"mhuxton3d@discovery.com"},
{"username":"hlanston3e","password":"jj9VT0","email":"coxbe3e@pen.io"},
{"username":"cblasli3f","password":"g3FlmJQ","email":"hmarmon3f@ucoz.com"},
{"username":"gbromet3g","password":"shqysmadSGX","email":"tclousley3g@oakley.com"},
{"username":"fbassick3h","password":"QquW0s","email":"fkapelhoff3h@goo.gl"},
{"username":"ttwamley3i","password":"pUFftXZnz","email":"hsporner3i@163.com"},
{"username":"dbinham3j","password":"snPJJGeTwTf","email":"hfintoph3j@redcross.org"},
{"username":"tdebernardis3k","password":"E9y2yQyjg","email":"tandreuzzi3k@bing.com"},
{"username":"rmcevay3l","password":"Fo7BbC","email":"tstallebrass3l@howstuffworks.com"},
{"username":"cmckevitt3m","password":"w4CtDFrRvIAP","email":"afolker3m@ocn.ne.jp"},
{"username":"cgalletly3n","password":"6sXhkkmX","email":"awainer3n@samsung.com"},
{"username":"tcapaldi3o","password":"YISR9ju","email":"scleal3o@berkeley.edu"},
{"username":"rmacdonnell3p","password":"z7mIfd4SDo","email":"nolifard3p@mapy.cz"},
{"username":"tbottjer3q","password":"P8b1ARqgro2","email":"fderrington3q@yahoo.com"},
{"username":"rslyne3r","password":"xMiOHykoCUy","email":"epyke3r@free.fr"},
{"username":"kfry3s","password":"YfOcnN","email":"mwilkisson3s@sciencedirect.com"},
{"username":"astockley3t","password":"5uP4CwkvOAOq","email":"amunkley3t@tiny.cc"},
{"username":"ncolombier3u","password":"eOvmk3V16qo","email":"meatherton3u@tamu.edu"},
{"username":"strodd3v","password":"d2ER9n","email":"cbrazil3v@zdnet.com"},
{"username":"bojeda3w","password":"FKyl7nFX1Z","email":"xkirvell3w@google.co.jp"},
{"username":"swatmough3x","password":"hLJUHQE","email":"mlamzed3x@un.org"},
{"username":"cbigland3y","password":"8D6KgFNmih","email":"cstower3y@cdbaby.com"},
{"username":"lbrakewell3z","password":"g2LQjxk","email":"lcraythorn3z@yandex.ru"},
{"username":"agrundwater40","password":"PdB5Op9","email":"gflahy40@t.co"},
{"username":"tbaraja41","password":"jwGRluk8uu","email":"kcummine41@rambler.ru"},
{"username":"lrayment42","password":"W5xr1Dj6QZYr","email":"gjoddens42@smugmug.com"},
{"username":"fmaber43","password":"QxZJHVIyyos","email":"cshottin43@boston.com"},
{"username":"cnorval44","password":"pvNtDZEr3jd","email":"ecoda44@desdev.cn"},
{"username":"rkupper45","password":"tXeOfU","email":"aunworth45@prweb.com"},
{"username":"prubin46","password":"AFzz9BkOqc4G","email":"salbrecht46@yahoo.com"},
{"username":"nmordon47","password":"bpv3ZkcA","email":"mmecozzi47@de.vu"},
{"username":"sjacqueminot48","password":"tFPz1iLK","email":"fkybbye48@symantec.com"},
{"username":"msanper49","password":"0z4b5JjNHvw","email":"msaban49@sitemeter.com"},
{"username":"hmeikle4a","password":"6g4snwDZ","email":"jcustance4a@statcounter.com"},
{"username":"hlowdes4b","password":"vC6CVi","email":"cgalton4b@ihg.com"},
{"username":"rbrisard4c","password":"MO2qCdLe","email":"tmcnea4c@cdc.gov"},
{"username":"cscogin4d","password":"82JDkndlch","email":"abendtsen4d@ustream.tv"},
{"username":"mpatershall4e","password":"mbCohwQWJG","email":"fsimmans4e@nytimes.com"},
{"username":"mlaughtisse4f","password":"XbiTU7","email":"mlonder4f@weather.com"},
{"username":"khacket4g","password":"CZQtQvK1","email":"bhalbard4g@dailymotion.com"},
{"username":"jbaraclough4h","password":"acorp06","email":"vboggish4h@howstuffworks.com"},
{"username":"rpaye4i","password":"qHyZnJ","email":"aeasterling4i@wp.com"},
{"username":"adrewclifton4j","password":"Z1KcW8","email":"klauridsen4j@miitbeian.gov.cn"},
{"username":"nchatelain4k","password":"TTLfGE5Wj","email":"ecoldrick4k@weather.com"},
{"username":"njouannisson4l","password":"e2pMhE40","email":"mdeaton4l@typepad.com"},
{"username":"ljerrold4m","password":"VZYghi","email":"mlyddiatt4m@shutterfly.com"},
{"username":"eglendenning4n","password":"2VI72d","email":"whutfield4n@ed.gov"},
{"username":"abennallck4o","password":"4qr9MI9bX1wY","email":"tsamter4o@cafepress.com"},
{"username":"ybrumble4p","password":"i1y2aE5","email":"gcromley4p@uol.com.br"},
{"username":"tfrudd4q","password":"UVsEA8bUs","email":"seccleston4q@qq.com"},
{"username":"blegalle4r","password":"9tt4vradN","email":"ckorpal4r@kickstarter.com"},
{"username":"esteeples4s","password":"a8jNvnRBM","email":"mlillford4s@slideshare.net"},
{"username":"scorre4t","password":"c9yr1v","email":"kivannikov4t@sourceforge.net"},
{"username":"lbelderfield4u","password":"cTM5DT","email":"dstenhouse4u@wired.com"},
{"username":"amcarthur4v","password":"DWGgYQP","email":"hburfield4v@dell.com"},
{"username":"yrominov4w","password":"pKsz0A","email":"astorrs4w@imdb.com"},
{"username":"pwhyke4x","password":"xHPwVsFNbj","email":"ebeech4x@jugem.jp"},
{"username":"spiscopiello4y","password":"rB3uuogbolZ","email":"abaudone4y@technorati.com"},
{"username":"spether4z","password":"luOMIO4Zq","email":"dsille4z@freewebs.com"},
{"username":"fsinnocke50","password":"A9JWDNp5kCv","email":"abuard50@microsoft.com"},
{"username":"wfulford51","password":"iS6c8xFhVQ9Y","email":"batlee51@nationalgeographic.com"},
{"username":"ggibbon52","password":"9pZjCblHDN6T","email":"ddelabarre52@yelp.com"},
{"username":"ahessentaler53","password":"VItiMp","email":"bvyel53@unc.edu"},
{"username":"dtedstone54","password":"IUzHsOAofr67","email":"nsell54@wufoo.com"},
{"username":"jleithharvey55","password":"LMy7DvEsEQ6U","email":"zcarass55@rambler.ru"},
{"username":"ekingswold56","password":"gaarpMhM8N","email":"kstrethill56@weather.com"},
{"username":"cdobie57","password":"gG2y1g64NW","email":"ldevereu57@time.com"},
{"username":"ldanilchik58","password":"JmzsIF","email":"amelland58@huffingtonpost.com"},
{"username":"swansbury59","password":"wtxXOMzi2GM","email":"dfurzey59@wunderground.com"},
{"username":"jrathbourne5a","password":"AWa1OZ","email":"tblees5a@reverbnation.com"},
{"username":"syong5b","password":"8C8q1hp","email":"rbaytrop5b@dyndns.org"},
{"username":"cpridden5c","password":"MDcM9MK2XI","email":"bfloat5c@ehow.com"},
{"username":"sswinerd5d","password":"Jxjd5f","email":"lhellin5d@jalbum.net"},
{"username":"athormwell5e","password":"3yXymoUGAXkZ","email":"anovik5e@cisco.com"},
{"username":"mtompkins5f","password":"zGpn3LXNIrt9","email":"amitchely5f@php.net"},
{"username":"ccoleman5g","password":"NVLnUbGlrx5s","email":"pjepp5g@un.org"},
{"username":"loveral5h","password":"NmTM2BvxkEap","email":"pibotson5h@indiatimes.com"},
{"username":"fbisp5i","password":"71vH5Pdx","email":"jbowdidge5i@msu.edu"},
{"username":"epocklington5j","password":"3CQPFXm4hK","email":"lconstantine5j@infoseek.co.jp"},
{"username":"jyakovich5k","password":"WZlgyn","email":"kboothroyd5k@jiathis.com"},
{"username":"emcgowing5l","password":"UdzEG5tE7c","email":"mtwist5l@bloglovin.com"},
{"username":"tgrannell5m","password":"vVeUtobR","email":"mnoye5m@yelp.com"},
{"username":"cmulqueen5n","password":"ePBSIfybVsgB","email":"ascamaden5n@oracle.com"},
{"username":"nmechem5o","password":"lqawByQ","email":"rsweetman5o@globo.com"},
{"username":"lfullagar5p","password":"guKZZva","email":"dbethel5p@noaa.gov"},
{"username":"ktench5q","password":"lTqIRwXj","email":"iosmint5q@mlb.com"},
{"username":"lsloper5r","password":"cNnyc3FO4","email":"hluckie5r@wufoo.com"},
{"username":"tmcguinley5s","password":"kQplx88U0h3Q","email":"ddezamora5s@vinaora.com"},
{"username":"pbloomfield5t","password":"SRHOsjDLsG","email":"cdawdry5t@google.com.hk"},
{"username":"rhemmingway5u","password":"eHfmKPf","email":"wmcardell5u@thetimes.co.uk"},
{"username":"bcouldwell5v","password":"ksdQlNvf9m","email":"kmasterman5v@google.fr"},
{"username":"mopie5w","password":"hO4DYyZc","email":"ahotton5w@businesswire.com"},
{"username":"kbinnell5x","password":"8u4EfWF","email":"omoyce5x@prlog.org"},
{"username":"mjeandel5y","password":"rF37xPif","email":"nchinnock5y@furl.net"},
{"username":"ogergus5z","password":"CRGVbFhq","email":"yperigeaux5z@sciencedaily.com"},
{"username":"iloads60","password":"7njPJ8Lk","email":"gcade60@amazon.com"},
{"username":"vbroady61","password":"obLFDB","email":"scarrigan61@dagondesign.com"},
{"username":"zmainz62","password":"1eF9keMAbzKj","email":"tdenkel62@ibm.com"},
{"username":"mwestwell63","password":"TqUWkNYJnG6","email":"hfoat63@rediff.com"},
{"username":"lportch64","password":"X5R4WQ","email":"naldrin64@github.com"},
{"username":"hbunt65","password":"Iu0iVnu7","email":"jbrigg65@huffingtonpost.com"},
{"username":"aboughtflower66","password":"Kb7gpzF9","email":"grosewall66@parallels.com"},
{"username":"pmair67","password":"nX0VFHdIo9","email":"reldrett67@cbc.ca"},
{"username":"anibloe68","password":"oIZcXk","email":"keley68@discovery.com"},
{"username":"kmackimmie69","password":"oBWzrxKCozy","email":"khumes69@cbsnews.com"},
{"username":"ndabs6a","password":"SK3uvDLvXV","email":"jmenilove6a@printfriendly.com"},
{"username":"cshillinglaw6b","password":"uvntHO3r7N","email":"kabrahamoff6b@so-net.ne.jp"},
{"username":"fmeasor6c","password":"IWXZkE3G","email":"ceuels6c@mayoclinic.com"},
{"username":"pclucas6d","password":"OjeJmdRpDG","email":"kedowes6d@taobao.com"},
{"username":"sbraidford6e","password":"CNOZEET","email":"estirgess6e@ovh.net"},
{"username":"jslora6f","password":"k41KkoZX4Jaj","email":"zhebard6f@blinklist.com"},
{"username":"cpasmore6g","password":"l96VaQ1b","email":"fadnet6g@fastcompany.com"},
{"username":"rpretor6h","password":"UOHy0w1DH","email":"slukock6h@ocn.ne.jp"},
{"username":"nmedcalf6i","password":"tqPxfC","email":"laskham6i@examiner.com"},
{"username":"kextall6j","password":"afzvIOV","email":"nroantree6j@studiopress.com"},
{"username":"biacovino6k","password":"B757sJmB","email":"kmccloy6k@t-online.de"},
{"username":"klotwich6l","password":"ugMkhRp","email":"fwitherow6l@desdev.cn"},
{"username":"pmarciek6m","password":"a6FWs0Qr","email":"khowells6m@hubpages.com"},
{"username":"cliverock6n","password":"hJJtz09mQ","email":"tcesco6n@123-reg.co.uk"},
{"username":"mpreshaw6o","password":"Gjq3XwUVuaa","email":"tcrookshanks6o@google.com.au"},
{"username":"dhowselee6p","password":"JBaHe6tOfu1","email":"jtryme6p@elegantthemes.com"},
{"username":"aorteu6q","password":"U1Prtg","email":"hpiola6q@boston.com"},
{"username":"flescop6r","password":"F0KHfYjfbl","email":"ccrichley6r@theglobeandmail.com"},
{"username":"bdavidesco6s","password":"TdnJCIpd","email":"areynault6s@tuttocitta.it"},
{"username":"nsteggles6t","password":"rV8UVVstX3","email":"dgunthorpe6t@addthis.com"},
{"username":"jhuburn6u","password":"K69JijyCwu2","email":"htuckie6u@shinystat.com"},
{"username":"sdomange6v","password":"4MJPnl","email":"dkeenlayside6v@marketwatch.com"},
{"username":"npietesch6w","password":"n0vGLBO5o","email":"pnares6w@topsy.com"},
{"username":"gsall6x","password":"8oRuiSPH","email":"kabarough6x@spiegel.de"},
{"username":"cmattevi6y","password":"fxYhCB7","email":"tmantripp6y@tiny.cc"},
{"username":"jiwaszkiewicz6z","password":"kcumKCB","email":"igauvain6z@marriott.com"},
{"username":"lrickets70","password":"hsMrzpT","email":"trhodef70@blogs.com"},
{"username":"mhogben71","password":"1hn1WofLpfvA","email":"eohowbane71@ox.ac.uk"},
{"username":"tcordier72","password":"nTMObB","email":"kschaffler72@jigsy.com"},
{"username":"rsobtka73","password":"JrHxOY","email":"fblennerhassett73@shareasale.com"},
{"username":"cbaudains74","password":"CjV14z9hveEN","email":"cagge74@forbes.com"},
{"username":"alindstrom75","password":"0Z8AmVSlM","email":"mbowdrey75@cocolog-nifty.com"},
{"username":"tjepensen76","password":"vpr6K8wnM","email":"ahelder76@businesswire.com"},
{"username":"jdraysay77","password":"23uLEcmNv","email":"amabbot77@google.pl"},
{"username":"cdufer78","password":"nB2CzathAJ","email":"tgarm78@unesco.org"},
{"username":"rcolbron79","password":"kKwt5zbOq776","email":"atudor79@netscape.com"},
{"username":"gnealey7a","password":"mUUWBZR8DU","email":"cwhillock7a@shinystat.com"},
{"username":"tanthoney7b","password":"91D7VqrTWH7","email":"amcdonough7b@chron.com"},
{"username":"dproudler7c","password":"ePM4VQdn6n","email":"rreace7c@newsvine.com"},
{"username":"fcuphus7d","password":"r8kMMcU04uK","email":"scuer7d@sun.com"},
{"username":"noulner7e","password":"yvRxXr","email":"pjosebury7e@msn.com"},
{"username":"jcosten7f","password":"ZrE3YFp","email":"vdallosso7f@cisco.com"},
{"username":"mdavers7g","password":"7pThi1Fii3Ys","email":"pohrt7g@psu.edu"},
{"username":"lneller7h","password":"BreHIfByTqP","email":"cjenkins7h@usa.gov"},
{"username":"dstonebanks7i","password":"vXJV9vw","email":"jmcgahey7i@imageshack.us"},
{"username":"lsabater7j","password":"jXUUx6","email":"timos7j@shareasale.com"},
{"username":"aokell7k","password":"BobM1dExZaI","email":"cgreenfield7k@sun.com"},
{"username":"nkeeltagh7l","password":"GgFink","email":"chirche7l@soup.io"},
{"username":"aruddiforth7m","password":"akqOTThenx","email":"nlazare7m@wikispaces.com"},
{"username":"nrheaume7n","password":"peokovMsZF","email":"nhobgen7n@furl.net"},
{"username":"moliphand7o","password":"iAXxqdy","email":"gstappard7o@noaa.gov"},
{"username":"dshoubridge7p","password":"0NJP0U3EJxq6","email":"wberka7p@businesswire.com"},
{"username":"jdanilyuk7q","password":"oM7oXdX7","email":"tstarbuck7q@umn.edu"},
{"username":"chaile7r","password":"srFW93","email":"ablakden7r@sun.com"},
{"username":"msommerling7s","password":"jwkUA4g2Z","email":"ngarnall7s@dot.gov"},
{"username":"tgodard7t","password":"H9Iag34hC","email":"ebulluck7t@plala.or.jp"},
{"username":"qjolland7u","password":"edixzA0A0","email":"cramsay7u@wiley.com"},
{"username":"glynds7v","password":"dx70nM7v0","email":"gaers7v@amazon.com"},
{"username":"rkleinstern7w","password":"tiu1ZF","email":"ofidgeon7w@networksolutions.com"},
{"username":"visard7x","password":"N192p7","email":"mforton7x@ca.gov"},
{"username":"mpougher7y","password":"MpR4D8","email":"mknutsen7y@wufoo.com"},
{"username":"amould7z","password":"65PknmTjX1Du","email":"wkaley7z@deliciousdays.com"},
{"username":"ddevinn80","password":"HkgyXT","email":"asygrove80@google.ca"},
{"username":"cgadney81","password":"lljX61K","email":"rdaubney81@arstechnica.com"},
{"username":"lsanpher82","password":"X5t44U","email":"llunny82@princeton.edu"},
{"username":"aaiston83","password":"FGnSAfBnjm","email":"tsnelgrove83@w3.org"},
{"username":"elamlin84","password":"nPaX0ZjDx","email":"dhodjetts84@dedecms.com"},
{"username":"ssmedmoor85","password":"jGHUqOVE","email":"astanesby85@deviantart.com"},
{"username":"mlikly86","password":"ZI0a3AH8m","email":"sverson86@cbc.ca"},
{"username":"ddenisard87","password":"OjDCr6","email":"akornes87@ucoz.ru"},
{"username":"asergent88","password":"rHxjo897pNaU","email":"lcotte88@hao123.com"},
{"username":"hstodit89","password":"5WMlIx","email":"tnicklin89@bloglovin.com"},
{"username":"khayler8a","password":"HbzqoHktFtn7","email":"jvolker8a@slate.com"},
{"username":"ibuckeridge8b","password":"AFmptKpGMr","email":"egalliard8b@theguardian.com"},
{"username":"rtattershaw8c","password":"BSW5TcgE9vNZ","email":"cvermer8c@paypal.com"},
{"username":"sdomokos8d","password":"FFktsHUt6","email":"mboog8d@live.com"},
{"username":"astraine8e","password":"l1WrI1w32","email":"mblue8e@google.cn"},
{"username":"bgoare8f","password":"nyF7CJXySLMV","email":"yphythien8f@ow.ly"},
{"username":"frumens8g","password":"XnvIiKl","email":"fszymon8g@squarespace.com"},
{"username":"mswaysland8h","password":"8XQQogg","email":"gmacsween8h@dagondesign.com"},
{"username":"kmoyce8i","password":"fCrkA4p","email":"doldis8i@timesonline.co.uk"},
{"username":"datwool8j","password":"UAG8Odoxg","email":"bfippe8j@census.gov"},
{"username":"hrillstone8k","password":"Tq0zUP7a00","email":"roshee8k@bing.com"},
{"username":"ilarmett8l","password":"2RTTh5","email":"emeardon8l@boston.com"},
{"username":"btume8m","password":"LceQrBUb","email":"ldicken8m@cdbaby.com"},
{"username":"lklimecki8n","password":"eP4Ydy2QcJ","email":"mgodbald8n@chicagotribune.com"},
{"username":"cbirckmann8o","password":"MuBudBjZCbD","email":"kdeverson8o@amazon.com"},
{"username":"bshakesby8p","password":"Ox9vCQq3HG","email":"atootal8p@51.la"},
{"username":"kdictus8q","password":"8gq0Ts","email":"acereceres8q@friendfeed.com"},
{"username":"rcawkwell8r","password":"hfqS6MK1lr8I","email":"krameau8r@unicef.org"},
{"username":"aganforth8s","password":"3XKXSE","email":"smorpeth8s@google.com.au"},
{"username":"bdonnersberg8t","password":"2sui1zw47","email":"gmingaud8t@woothemes.com"},
{"username":"mchucks8u","password":"MMst2C","email":"gjameson8u@myspace.com"},
{"username":"rrottgers8v","password":"43GltUGCHH","email":"agasnoll8v@hubpages.com"},
{"username":"dlaville8w","password":"NSgBZBPsbJO","email":"bzeale8w@ox.ac.uk"},
{"username":"wdinneges8x","password":"Hq3HSx4dKnk5","email":"apackham8x@cloudflare.com"},
{"username":"ncantrell8y","password":"oSSM7qm2DX","email":"gsandiland8y@narod.ru"},
{"username":"jscotchbrook8z","password":"3UgEBilT","email":"roliva8z@acquirethisname.com"},
{"username":"fempleton90","password":"IzRMUExG6","email":"olazar90@yellowbook.com"},
{"username":"wtoothill91","password":"rxUroODrIC","email":"dreford91@theatlantic.com"},
{"username":"hgorvette92","password":"cR5PHm7weME","email":"lgurling92@4shared.com"},
{"username":"mverling93","password":"GAubk2QGdp3","email":"dmckeran93@drupal.org"},
{"username":"dhenkens94","password":"exEUJYcTR","email":"sklosser94@un.org"},
{"username":"mbeuscher95","password":"tHGKaM8OD2O","email":"gcranmere95@123-reg.co.uk"},
{"username":"bloadsman96","password":"clcatS","email":"jkeneforde96@51.la"},
{"username":"hgoggey97","password":"Rsqb14XDdcN","email":"cgrundell97@comsenz.com"},
{"username":"lemeney98","password":"gHFEMaY","email":"sbollum98@telegraph.co.uk"},
{"username":"cbrizell99","password":"kWxPJnj2QVl","email":"sopdenorth99@un.org"},
{"username":"lrandalson9a","password":"2iZfqJsMk5V","email":"klarham9a@google.de"},
{"username":"naspinal9b","password":"rWEcgTEbdH","email":"ethebes9b@ucoz.ru"},
{"username":"glacroux9c","password":"U1ZutUNu","email":"bemilien9c@studiopress.com"},
{"username":"mmiddis9d","password":"ow6atL","email":"rgoretti9d@hibu.com"},
{"username":"anettles9e","password":"wCFubjn","email":"satkirk9e@wunderground.com"},
{"username":"tpascoe9f","password":"hjwkDjVAm","email":"jiglesias9f@blogspot.com"},
{"username":"ncordeiro9g","password":"KSBzlHxjzny","email":"kkeasey9g@so-net.ne.jp"},
{"username":"rferrucci9h","password":"V8l8i9BQDla","email":"atakle9h@constantcontact.com"},
{"username":"mlancastle9i","password":"eOFMvOlYcvr9","email":"emelvin9i@prlog.org"},
{"username":"hlimb9j","password":"45oTVsv6QKe","email":"gnineham9j@stanford.edu"},
{"username":"istud9k","password":"diByT5etyzt","email":"keslie9k@addtoany.com"},
{"username":"amilksop9l","password":"cxpcp3o","email":"abrazier9l@tinyurl.com"},
{"username":"astaveley9m","password":"ew9jGloUwti","email":"ggiacopelo9m@google.com.br"},
{"username":"oday9n","password":"rBXW0pg","email":"nmilstead9n@salon.com"},
{"username":"coldey9o","password":"zOfSJC","email":"bcurrum9o@surveymonkey.com"},
{"username":"twinterson9p","password":"9riP30FmtL","email":"rcaress9p@liveinternet.ru"},
{"username":"rtoupe9q","password":"NW6ZQ8","email":"ncopplestone9q@blogs.com"},
{"username":"mchaters9r","password":"Tt282ds4GvVi","email":"elesser9r@dailymail.co.uk"},
{"username":"nwarin9s","password":"sPPRtHLAKa7E","email":"satyeo9s@theglobeandmail.com"},
{"username":"fclewlow9t","password":"TnhYVe0hWGzq","email":"wfinnimore9t@bigcartel.com"},
{"username":"kfrascone9u","password":"ugNSW7DP","email":"mkingcott9u@tripadvisor.com"},
{"username":"tclouston9v","password":"dQnYvzVqFfD","email":"cderrico9v@github.io"},
{"username":"isergeaunt9w","password":"qxJ4lXTxyT4Q","email":"mcastenda9w@ibm.com"},
{"username":"rmungan9x","password":"j5ZT1pA","email":"nbrauner9x@sciencedirect.com"},
{"username":"eayscough9y","password":"8CqJPxwq","email":"mlachaize9y@walmart.com"},
{"username":"awestfrimley9z","password":"aiN2wpU1ljC","email":"ehagergham9z@uol.com.br"},
{"username":"dchurchousea0","password":"WdRDtAx0f","email":"tlagesa0@smugmug.com"},
{"username":"ibalmaa1","password":"4grRVI3N0d","email":"mmalta1@wiley.com"},
{"username":"tbellhangera2","password":"PejN8W2F1fl","email":"bscampa2@usgs.gov"},
{"username":"cfryatta3","password":"hGbSuE","email":"cbressona3@trellian.com"},
{"username":"ipyrtona4","password":"9MntJz1dDF","email":"tdavineta4@nytimes.com"},
{"username":"abullersa5","password":"dh6seQIRhR","email":"dchalonera5@privacy.gov.au"},
{"username":"cspriggena6","password":"B3ahPg6N","email":"jbromella6@soup.io"},
{"username":"vlackmanna7","password":"pQfgBbSvq9F","email":"eastina7@msu.edu"},
{"username":"tledgistera8","password":"I95oDvCll1i","email":"fpfliegera8@jalbum.net"},
{"username":"tdibbina9","password":"xaH0Os","email":"cmawda9@sakura.ne.jp"},
{"username":"dwhitfordaa","password":"KqU1S0D","email":"gitzhakiaa@nyu.edu"},
{"username":"lchowneab","password":"Y0jx3i","email":"zduckeringab@macromedia.com"},
{"username":"cmacmoyerac","password":"y4Hwh9iCIi1","email":"jodonohueac@mtv.com"},
{"username":"wgoldsteinad","password":"1VVoiyg","email":"nnealonad@tamu.edu"},
{"username":"mlumsdaleae","password":"QL1YS8KGfRHs","email":"wkersawae@g.co"},
{"username":"tbeckenhamaf","password":"8fILTiCr0l","email":"kcollobyaf@yolasite.com"},
{"username":"rbirnieag","password":"5ghzy4wDKk4","email":"rottleyag@tripadvisor.com"},
{"username":"llaightah","password":"GcUYxlV","email":"eclamoah@google.cn"},
{"username":"smarranai","password":"8TEbVUX","email":"agilardoneai@gravatar.com"},
{"username":"mcheelaj","password":"pi1mVC6Db2L","email":"khusbyaj@macromedia.com"},
{"username":"pdanieliak","password":"jJmbN68M","email":"egasconeak@virginia.edu"},
{"username":"jbanfordal","password":"HRPTnwFkEY","email":"jlaceyal@globo.com"},
{"username":"jstrowlgeram","password":"OH3z0qjsz","email":"dszymanowskiam@sciencedirect.com"},
{"username":"bcaldwallan","password":"49JrZD9vO","email":"mbousteadan@omniture.com"},
{"username":"pfrickeyao","password":"I8bw7P","email":"cdumingosao@uol.com.br"},
{"username":"icockeap","password":"qCCMjpd","email":"draulstoneap@smugmug.com"},
{"username":"adrinkallaq","password":"v7RQF5ia","email":"lcissellaq@microsoft.com"},
{"username":"rwandrackar","password":"mw7a95sulc","email":"fshakesbyear@odnoklassniki.ru"},
{"username":"sfaheyas","password":"DDE8WAgQy","email":"ghayneas@ucsd.edu"},
{"username":"ksimmat","password":"Aau5vRz","email":"khawsonat@quantcast.com"},
{"username":"bfinkleau","password":"NWJ0pnoXLlj","email":"nstuerau@mlb.com"},
{"username":"kochiltreeav","password":"8QcXIMyY","email":"wbreitav@behance.net"},
{"username":"jfancetaw","password":"imAoqPwt6Am","email":"spickwellaw@yelp.com"},
{"username":"dminelliax","password":"aNE1FFu","email":"amosbyax@samsung.com"},
{"username":"ddeleekay","password":"yuK3pRR","email":"jthorbyay@ted.com"},
{"username":"dkilneraz","password":"SZwnGShN","email":"shunstonaz@psu.edu"},
{"username":"fpapisb0","password":"nLJY5yb2jz","email":"seschelleb0@free.fr"},
{"username":"aperazzob1","password":"tjkoAzzvNB8J","email":"rledsonb1@tripod.com"},
{"username":"cvarndallb2","password":"P66JdBL3","email":"lraddenb2@typepad.com"},
{"username":"nyorkstonb3","password":"myTcXG","email":"cstanyonb3@chron.com"},
{"username":"gheaslyb4","password":"Upk6JY","email":"asilbermannb4@timesonline.co.uk"},
{"username":"wkemmonsb5","password":"kdpJro3Ob","email":"csabieb5@sbwire.com"},
{"username":"rivicb6","password":"khMOAMh","email":"imorchb6@mapy.cz"},
{"username":"arushsorthb7","password":"BjIOGwCK4r","email":"bprujeanb7@senate.gov"},
{"username":"csillimanb8","password":"cG4TzHmx9y8","email":"rcatchersideb8@bbc.co.uk"},
{"username":"nrenardb9","password":"griSiL7","email":"jdrainsb9@issuu.com"},
{"username":"llockhurstba","password":"KHGV1kx7f","email":"mwisdomba@virginia.edu"},
{"username":"dbiddlestonbb","password":"teHEg11","email":"erathbonebb@e-recht24.de"},
{"username":"bmaslinbc","password":"GygS5z6y","email":"moveybc@ning.com"},
{"username":"scastagnonebd","password":"NffmctxoTRz","email":"rpollicotebd@arizona.edu"},
{"username":"aimpletonbe","password":"zdRYif","email":"mlamplbe@amazon.co.uk"},
{"username":"sferrarinbf","password":"yy7V6kHfZoi","email":"mrannerbf@sohu.com"},
{"username":"aohenerybg","password":"JD4VRK","email":"smosconbg@yelp.com"},
{"username":"atrevaskissbh","password":"XIaFrzwN","email":"ewelfairbh@pen.io"},
{"username":"cdaintonbi","password":"sEiOg8t","email":"pbrosinibi@upenn.edu"},
{"username":"hblanninbj","password":"0oROwEEDCAHC","email":"daskewbj@geocities.com"},
{"username":"cdobsonbk","password":"f2dBmHF","email":"shendinbk@washington.edu"},
{"username":"rpietrasikbl","password":"0Qw56oVf","email":"lripperbl@google.it"},
{"username":"npillingtonbm","password":"95UJ7FTS","email":"jgearybm@themeforest.net"},
{"username":"cblankmanbn","password":"r7EU652R","email":"ctrowellbn@psu.edu"},
{"username":"cdornbo","password":"6LXkIv","email":"tovettbo@wunderground.com"},
{"username":"bbenduhnbp","password":"zM6xkRtVJJT","email":"jdudbridgebp@printfriendly.com"},
{"username":"dbraidfordbq","password":"XbfXF9","email":"vjosupeitbq@quantcast.com"},
{"username":"dellistonbr","password":"2fZVeRcyH","email":"hedensorbr@printfriendly.com"},
{"username":"fmattiabs","password":"3A6tan","email":"ffitzgibbonbs@businessweek.com"},
{"username":"slaysonbt","password":"iPgNM7FWs","email":"wbrandsbt@so-net.ne.jp"},
{"username":"cgingoldbu","password":"MquI7Pkwf","email":"gskelbeckbu@ox.ac.uk"},
{"username":"bbrookerbv","password":"OnDzV931","email":"ajentinbv@arstechnica.com"},
{"username":"otourvillebw","password":"rzr67I","email":"rbristerbw@php.net"},
{"username":"jwhybornebx","password":"GzgVHogCN","email":"ebirrelbx@sakura.ne.jp"},
{"username":"cedenby","password":"aplnFg3j","email":"sspongby@reverbnation.com"},
{"username":"acufflinbz","password":"BdVc4j34E","email":"bgilardibz@berkeley.edu"},
{"username":"rallredc0","password":"FPZCQ6XP9bPq","email":"ecargillc0@nifty.com"},
{"username":"dtarbettc1","password":"xEtOHAsNlN7q","email":"khegdonnec1@cnet.com"},
{"username":"fclampec2","password":"gBgq0A","email":"agoodbarnec2@spotify.com"},
{"username":"mgallimorec3","password":"S3dfpj2N","email":"sfussellc3@timesonline.co.uk"},
{"username":"araittc4","password":"gyTTLqV","email":"ppietraszekc4@dagondesign.com"},
{"username":"mumneyc5","password":"6BEJyEUs","email":"emiddlemassc5@xing.com"},
{"username":"apettisc6","password":"cBt8dVdfCaOm","email":"aelementc6@upenn.edu"},
{"username":"tegglec7","password":"hRrFd6","email":"fmalebyc7@amazon.co.uk"},
{"username":"oleppingtonc8","password":"JafaKJFc6P","email":"gmaultc8@nationalgeographic.com"},
{"username":"bsciacovellic9","password":"Nkhb36j2","email":"croscampc9@nature.com"},
{"username":"avosperca","password":"rrMrCkuMy","email":"gantosca@ask.com"},
{"username":"valbioncb","password":"QwpsPP","email":"lbernardoncb@cafepress.com"},
{"username":"cdingsdalecc","password":"p6qJ8rDsI","email":"afessbycc@craigslist.org"},
{"username":"bviggarscd","password":"WDJCaP","email":"jassurcd@hhs.gov"},
{"username":"psevillece","password":"bHGKvU3Yz6","email":"boreagance@house.gov"},
{"username":"ecrosscombecf","password":"6e2ZXpLk","email":"ctofflercf@dell.com"},
{"username":"osumptioncg","password":"TBODxAzHV","email":"gbafordcg@phpbb.com"},
{"username":"ebilyardch","password":"PZHKYE","email":"legginsch@over-blog.com"},
{"username":"aikringillci","password":"X6JKbCt","email":"ppellingtonci@un.org"},
{"username":"kmackincj","password":"lC6ZD5jX","email":"astandfieldcj@newsvine.com"},
{"username":"ebeveredgeck","password":"Vxfepjt3","email":"gfoneck@time.com"},
{"username":"bslidecl","password":"4K6cgDk","email":"mdoneldcl@nytimes.com"},
{"username":"ckerincm","password":"vT30SajZ","email":"jconerdingcm@virginia.edu"},
{"username":"vbulleyncn","password":"0M8Pcr7Yh","email":"sstudcn@soup.io"},
{"username":"cbrasherco","password":"fYTw61Pov","email":"lbarbrookco@ucoz.ru"},
{"username":"ibatcheldercp","password":"Huq1bVWOBikn","email":"meveredcp@ted.com"},
{"username":"eivachyovcq","password":"XbahGj2p","email":"ishortocq@homestead.com"},
{"username":"gjordesoncr","password":"Ndcei0OS","email":"lorringecr@cbslocal.com"},
{"username":"skelleycs","password":"NraI8ceHMMn","email":"xharbidgecs@yellowpages.com"},
{"username":"jelvesct","password":"MdBg6TCl","email":"lguildct@mac.com"},
{"username":"lhammerbergercu","password":"9DMv6q","email":"lbrosemancu@seesaa.net"},
{"username":"rhurtcv","password":"FYPX0i","email":"gjouanetoncv@statcounter.com"},
{"username":"mbonhancw","password":"tAjvrA","email":"hsparkscw@furl.net"},
{"username":"tgoulborncx","password":"4q9hUvHdmM","email":"stichnercx@vk.com"},
{"username":"gcompfordcy","password":"gDAVdmDQi","email":"hplattscy@tumblr.com"},
{"username":"aderisleycz","password":"KMAA2om","email":"fgentnercz@360.cn"},
{"username":"rvicareyd0","password":"7BgdtW","email":"atieraneyd0@google.de"},
{"username":"rsearld1","password":"vjVpxFCVq","email":"ivickarsd1@com.com"},
{"username":"jglennd2","password":"Qni0DT","email":"rluckwelld2@va.gov"},
{"username":"clongmand3","password":"oCZcXcnx7D","email":"rkinnardd3@smugmug.com"},
{"username":"rdundind4","password":"AmFmwm7tTx","email":"jthoumasd4@state.gov"},
{"username":"rwaddamsd5","password":"sPJxKVDs5WHD","email":"csoutherelld5@google.ca"},
{"username":"kbeilbyd6","password":"gjVLBBZkVO7","email":"cdoryd6@cnet.com"},
{"username":"growcastled7","password":"SkM1QZjCEEK","email":"mcleftd7@tumblr.com"},
{"username":"pmoorcraftd8","password":"eYnUiYdX","email":"aheinzeld8@abc.net.au"},
{"username":"mshilld9","password":"UqLk9UGl9a","email":"lcadwelld9@xing.com"},
{"username":"ndurbinda","password":"2PghEPYki","email":"ebarockda@tripod.com"},
{"username":"tharsesdb","password":"mWbcT7","email":"ppietrowskidb@japanpost.jp"},
{"username":"kfriddc","password":"Img8ZCV0XC","email":"ccamblingdc@feedburner.com"},
{"username":"lmarcodd","password":"XzTHRoX0","email":"scastagnonedd@blinklist.com"},
{"username":"gmcgeede","password":"COC7hA","email":"jwoodwindde@themeforest.net"},
{"username":"dokellydf","password":"uNnCichhwwY6","email":"tsainsburybrowndf@squarespace.com"},
{"username":"abarnbydg","password":"rOytREB9D","email":"mpenricedg@cbsnews.com"},
{"username":"jyanyushkindh","password":"X6nzAeZwPXMb","email":"dmccoskerdh@histats.com"},
{"username":"tbilliarddi","password":"qEAsc3TzJh0W","email":"glearmountdi@sciencedirect.com"},
{"username":"kdemeaddj","password":"HRCTjQ9YVbN","email":"mivashechkindj@oaic.gov.au"},
{"username":"dpitherickdk","password":"tvuHk7g","email":"rbaskervilledk@meetup.com"},
{"username":"gsprostondl","password":"FJCdl07CTC","email":"lscraftondl@tmall.com"},
{"username":"bmcguirkdm","password":"UKZYxa","email":"cgovierdm@list-manage.com"},
{"username":"nbunkledn","password":"tn6pagD6i3j","email":"lbarrondn@seesaa.net"},
{"username":"mmacheldo","password":"Y0e94p","email":"sfurnivaldo@ehow.com"},
{"username":"lwetherbydp","password":"yuJqOcOoOKV","email":"lziebartdp@wisc.edu"},
{"username":"wsagardq","password":"TfR9s7H","email":"bmynerdq@hp.com"},
{"username":"tgirardetdr","password":"puoKkikTK","email":"hjoridr@unicef.org"},
{"username":"mhalledayds","password":"wNDfgcA","email":"hphillpds@godaddy.com"},
{"username":"gjurewiczdt","password":"079ub68B","email":"btremblaydt@mtv.com"},
{"username":"gloosdu","password":"Tm1WnCRF","email":"sbaskeyfielddu@nature.com"},
{"username":"kstanleydv","password":"LbxJK4Ew","email":"rmckeeversdv@blog.com"},
{"username":"xgorwooddw","password":"tfjzsMzQW","email":"dkinghornedw@indiegogo.com"},
{"username":"cbrededx","password":"ceZnyb","email":"idorracottdx@edublogs.org"},
{"username":"kkretschmerdy","password":"AaOIZRZLKV","email":"srosendy@oracle.com"},
{"username":"dkondratenkodz","password":"hYcYAfhwrGpc","email":"mrameldz@github.io"},
{"username":"qeliasene0","password":"YTkNf3tD5nI","email":"sgummoee0@cafepress.com"},
{"username":"dcrennelle1","password":"dUYl2ax","email":"dkarpfe1@istockphoto.com"},
{"username":"asurgisone2","password":"NFMSgulGg9","email":"cbaloghe2@t.co"},
{"username":"wbartalinie3","password":"fwWJdvAu","email":"gsedgemonde3@guardian.co.uk"},
{"username":"mcowderaye4","password":"aWZQFrBbc","email":"dbrazenore4@odnoklassniki.ru"},
{"username":"jtryee5","password":"HAMPOVCnqp","email":"jmccrowe5@ox.ac.uk"},
{"username":"rcrosskille6","password":"OMpKgYW","email":"jroberdse6@ibm.com"},
{"username":"ecarrecke7","password":"VfDvMNLi9","email":"cleedale7@cornell.edu"},
{"username":"kmacrowe8","password":"S8awUSzgF","email":"ashadrache8@ning.com"},
{"username":"imerite9","password":"ZokLk3KeO","email":"askoughe9@cnet.com"},
{"username":"dfarneyea","password":"V8vlyDdZ9nD","email":"hfoskinea@state.tx.us"},
{"username":"hgallyoneb","password":"nE15xp4lvGJ","email":"ktrokereb@nasa.gov"},
{"username":"sphebyec","password":"BhyC6TIO1tWK","email":"mbendixenec@mysql.com"},
{"username":"ascraneed","password":"UtLFMmLkpbO","email":"dbaudassoed@hc360.com"},
{"username":"ewellingee","password":"ZpFfZ7ajYM","email":"dgoodramee@soundcloud.com"},
{"username":"adowdaef","password":"WKtUzdRx7a","email":"adundendaleef@uiuc.edu"},
{"username":"cprazereg","password":"S1bAVLsor9QC","email":"dpreshoeg@mit.edu"},
{"username":"yballingeh","password":"Cu2KO6CG","email":"dfalooneh@washington.edu"},
{"username":"leltunei","password":"6Yz1yg3j4ZcR","email":"mkeuningei@google.nl"},
{"username":"lgulliventej","password":"0diMXdL","email":"nrentelllej@mediafire.com"},
{"username":"dmcilriachek","password":"AY9qV5ebz","email":"gdungeyek@japanpost.jp"},
{"username":"mjerromesel","password":"aqMlfJIqe","email":"gmaccrawel@wufoo.com"},
{"username":"sdewarem","password":"armYvk","email":"hwintonem@etsy.com"},
{"username":"bfeldereren","password":"viXjVn03PIE","email":"ktegelleren@census.gov"},
{"username":"fpiborneo","password":"7IhPGnDzOoM","email":"hblofieldeo@163.com"},
{"username":"gbendellep","password":"EZBkEZUKgU9","email":"hsaggsep@wisc.edu"},
{"username":"zhalmeq","password":"WVD0mazv","email":"cdraiseyeq@google.es"},
{"username":"gvasilmanover","password":"9nqnQ6fXRT","email":"mhukinser@apple.com"},
{"username":"mstandishbrookses","password":"iDq96TWWiaUo","email":"eubankses@nationalgeographic.com"},
{"username":"dkalinskyet","password":"VTDWMRQK","email":"mjosephset@1688.com"},
{"username":"abatripeu","password":"Evq2oI","email":"dhuckeleu@constantcontact.com"},
{"username":"rgawkesev","password":"b4356Q","email":"rblazaev@examiner.com"},
{"username":"stimlinew","password":"qmlR5o43XH","email":"cilyasew@abc.net.au"},
{"username":"aduffanex","password":"Wo7hZoZH0J","email":"gsheenex@google.co.jp"},
{"username":"mmixerey","password":"NnTJJxo55Hd","email":"fhanniganeey@google.cn"},
{"username":"gcloustonez","password":"u3trhTd","email":"lbearez@cpanel.net"},
{"username":"wlandersf0","password":"cpgVPtu2mU","email":"cmclagainf0@cdbaby.com"},
{"username":"cshuryf1","password":"0DlAM4lGB","email":"jrawesf1@umn.edu"},
{"username":"gridehalghf2","password":"oIlhdK1QSRp","email":"nsloweyf2@cbc.ca"},
{"username":"phickenf3","password":"6Ar4dp","email":"mmackenneyf3@washington.edu"},
{"username":"cilyuninf4","password":"oOx9OvI9B","email":"ialelsandrovichf4@unblog.fr"},
{"username":"ctilnef5","password":"vxizeFCjlo","email":"nmellhuishf5@freewebs.com"},
{"username":"scollingwoodf6","password":"ecu3lOloQKe","email":"swisdenf6@goodreads.com"},
{"username":"mkiralyf7","password":"NMUuQ6Bj","email":"loldmeadowf7@ft.com"},
{"username":"apaudinf8","password":"gu9YQwZOUNZq","email":"vgrunsonf8@facebook.com"},
{"username":"jworswickf9","password":"ZnhSn4S2H3W7","email":"nsneathf9@nationalgeographic.com"},
{"username":"cleahyfa","password":"Zqjww0giuMD","email":"bjosephovfa@google.ca"},
{"username":"odobrowolskifb","password":"mGz4MMM8X","email":"inovillfb@ycombinator.com"},
{"username":"fvivienfc","password":"88VwkHkDDm","email":"lparagreenfc@nymag.com"},
{"username":"nveltenfd","password":"axA40ejxWG","email":"ktigwellfd@purevolume.com"},
{"username":"tstrachanfe","password":"gBKrfgavw","email":"jpadgintonfe@ning.com"},
{"username":"jpaolazziff","password":"6oOIHmLtTd","email":"ggrouerff@ocn.ne.jp"},
{"username":"mmerrillfg","password":"qpgS7DhLnbK","email":"cmacmoyerfg@technorati.com"},
{"username":"syirrellfh","password":"lF6K755b","email":"smacguinessfh@businessweek.com"},
{"username":"kfehnerfi","password":"S8ddbu","email":"mrossanderfi@yale.edu"},
{"username":"cjonahfj","password":"hzAI43","email":"jdematteisfj@rakuten.co.jp"},
{"username":"dcufleyfk","password":"IZ8AUI9uo","email":"ikauffmanfk@amazon.co.uk"},
{"username":"ldewarefl","password":"hrDnX7DSgYv","email":"tlumsdalefl@dropbox.com"},
{"username":"tdietzfm","password":"YH81xxEq4tK","email":"kokinedyfm@wix.com"},
{"username":"lfairholmefn","password":"lTysSEkt6BSV","email":"mgeatorfn@theguardian.com"},
{"username":"wlacknerfo","password":"b1tYbY8","email":"wknapmanfo@nbcnews.com"},
{"username":"svasishchevfp","password":"REi1xept","email":"sfittesfp@home.pl"},
{"username":"hmasarratfq","password":"7aIYsxzR","email":"oroylancefq@cloudflare.com"},
{"username":"jcleevefr","password":"4VbtEJrmA","email":"jrivelesfr@forbes.com"},
{"username":"bgaymarfs","password":"Q1u4qeFnr","email":"cbootlandfs@wiley.com"},
{"username":"apedreschift","password":"3amioAFnK9D","email":"aacostaft@google.ca"},
{"username":"hgogganfu","password":"NbVpK5E9","email":"vcowtherdfu@tumblr.com"},
{"username":"cwilsteadfv","password":"uBF8tP","email":"bgarleyfv@moonfruit.com"},
{"username":"rpiscofw","password":"qEqtPDXGwz","email":"ahawickfw@biglobe.ne.jp"},
{"username":"lvolantfx","password":"Le8LUXMTohk","email":"pmasurelfx@dropbox.com"},
{"username":"ibernathfy","password":"hzOGV207Q7","email":"escarbarrowfy@boston.com"},
{"username":"laustickfz","password":"TTqqFKDW0L","email":"bdinesenfz@yale.edu"},
{"username":"mpankettmang0","password":"iubZdN003PCI","email":"nwinng0@deviantart.com"},
{"username":"bsidebothamg1","password":"TuQGxWDW1C","email":"bonealg1@ameblo.jp"},
{"username":"ccoulthardg2","password":"AR1yKE4R","email":"gbrunstang2@xing.com"},
{"username":"pmatkovicg3","password":"80IAxu","email":"sfuentesg3@twitter.com"},
{"username":"hgooderidgeg4","password":"3318kAob","email":"plefeaverg4@google.co.uk"},
{"username":"msowterg5","password":"uAT8EZUS","email":"aspentong5@paginegialle.it"},
{"username":"bdeblaseg6","password":"dZXuSOyFCZi","email":"mgrisewoodg6@umich.edu"},
{"username":"ncoleirog7","password":"2ZyNEr","email":"fbulgeng7@simplemachines.org"},
{"username":"jswayneg8","password":"V0CDX6zeH","email":"treisg8@techcrunch.com"},
{"username":"leastbyg9","password":"hQvDerUo","email":"wsiviterg9@dmoz.org"},
{"username":"kwaliszekga","password":"LARQdy","email":"mportugalga@wunderground.com"},
{"username":"dhammondgb","password":"GvuReLUlS9","email":"gstraniogb@irs.gov"},
{"username":"aolehanegc","password":"VnmYIGQXhUG3","email":"nberndsengc@shutterfly.com"},
{"username":"mogormangd","password":"0RthdgzkDhdJ","email":"jbingegd@hostgator.com"},
{"username":"iroebyge","password":"8MhAub5","email":"gbissetge@eventbrite.com"},
{"username":"gellingsworthgf","password":"mp00DS","email":"sbilsongf@joomla.org"},
{"username":"cearleygg","password":"MkpqWWfd","email":"jcroxtongg@umich.edu"},
{"username":"ohollowgh","password":"LNzJfH","email":"bslimmongh@tinypic.com"},
{"username":"cgilbertsongi","password":"Pvj7Apg","email":"amilletongi@diigo.com"},
{"username":"bgeesongj","password":"xRbDGp","email":"kduthygj@elpais.com"},
{"username":"lmountjoygk","password":"eOT1Iy4G","email":"eommundsengk@usa.gov"},
{"username":"vkermottgl","password":"T7if13dH","email":"fantunesgl@prweb.com"},
{"username":"madvanigm","password":"c4nA0wqD","email":"hcrimminsgm@mapquest.com"},
{"username":"cfanstonegn","password":"dJOEECOJ7","email":"fperellogn@weebly.com"},
{"username":"bschwandergo","password":"5rjZW7k00H8","email":"staphousego@google.de"},
{"username":"livimeygp","password":"7xispFbFD4Z","email":"etrevainsgp@vimeo.com"},
{"username":"bhugillgq","password":"C5KoBzwbYy9","email":"jitzkovwichgq@squarespace.com"},
{"username":"bschultzgr","password":"oymqAc3GpwE","email":"gsouthwickgr@goo.ne.jp"},
{"username":"dfuttergs","password":"ACeUgzvfYxx1","email":"alaitygs@omniture.com"},
{"username":"jdummettgt","password":"6Xiuhe","email":"jcottisfordgt@deliciousdays.com"},
{"username":"eolingu","password":"1x5z31epX","email":"gpalphreymangu@squarespace.com"},
{"username":"efullegv","password":"1chQl3n","email":"mingrahamgv@devhub.com"},
{"username":"ttrahargw","password":"z2vYutwTm","email":"rgronallergw@bizjournals.com"},
{"username":"tcornewgx","password":"y7TFeJ7","email":"adategx@boston.com"},
{"username":"qkillelaygy","password":"SnlOIH","email":"dmauntongy@facebook.com"},
{"username":"mcecigz","password":"u0Gd1E2sbWHG","email":"jdifrancecshigz@so-net.ne.jp"},
{"username":"egilluleyh0","password":"MGiucUxB","email":"obartolomeazzih0@fda.gov"},
{"username":"pmarchettih1","password":"68xJJhJog","email":"rhatherleyh1@constantcontact.com"},
{"username":"rsherburnh2","password":"qMfR4G7Zr","email":"glaiteh2@rediff.com"},
{"username":"emaccheyneh3","password":"JGlLFt5KH","email":"cfedorskih3@jalbum.net"},
{"username":"jcockremh4","password":"BWCsolZrgVY","email":"sburdonh4@hhs.gov"},
{"username":"gwilliamsonh5","password":"PEl5173","email":"kterbrugh5@comcast.net"},
{"username":"bfishleyh6","password":"yMLU12","email":"wmustchinh6@people.com.cn"},
{"username":"jmanochh7","password":"NUFPxsGi0K6t","email":"tnevilleh7@irs.gov"},
{"username":"cbohjeh8","password":"YgNNmkvyq","email":"mbiaggettih8@hc360.com"},
{"username":"codah9","password":"8fawKZ","email":"hpriestlandh9@chron.com"},
{"username":"ojendasha","password":"yGzhMeGbJWt","email":"atresiseha@abc.net.au"},
{"username":"egiacoppohb","password":"2jaH7OoZ","email":"speacockhb@zimbio.com"},
{"username":"bchamleyhc","password":"8FHz0HrDK2PX","email":"phuckerbehc@nasa.gov"},
{"username":"racorshd","password":"TE9eXoc","email":"ksaphirhd@free.fr"},
{"username":"khilletthe","password":"6aoy1JXJHW","email":"sloachhe@wiley.com"},
{"username":"ahairhf","password":"CcI1Qn","email":"eboswardhf@tripadvisor.com"},
{"username":"jcastiglionehg","password":"Uma6TI","email":"gcoffeehg@dot.gov"},
{"username":"dabadehh","password":"UqUSEd3k","email":"achristophershh@sbwire.com"},
{"username":"lreecehi","password":"RnJUMIo","email":"rpudanhi@cornell.edu"},
{"username":"gwadsworthhj","password":"nNgivY6","email":"aiozefovichhj@earthlink.net"},
{"username":"mvasyutinhk","password":"5B4BDghk8","email":"xalsinahk@hc360.com"},
{"username":"sdurberhl","password":"whnRwJ","email":"aweavinghl@canalblog.com"},
{"username":"sleilhm","password":"39Cuan","email":"mgablerhm@buzzfeed.com"},
{"username":"nbimshn","password":"66wiOZ","email":"ccouragehn@360.cn"},
{"username":"cfarmanho","password":"SqDSU9x","email":"agillisonho@ustream.tv"},
{"username":"ahastlerhp","password":"p4KeoDxX","email":"obecerrohp@sphinn.com"},
{"username":"fhutchinsonhq","password":"VCgDOyVDXl","email":"bannotthq@netscape.com"},
{"username":"rsprullhr","password":"QXq6MCIC","email":"sverryhr@feedburner.com"},
{"username":"conianshs","password":"nQQVJs7nN","email":"ldelasallehs@woothemes.com"},
{"username":"mwilmutht","password":"2xapMOB","email":"aharsantht@vinaora.com"},
{"username":"agaitunghu","password":"VegFtPe2Tul1","email":"hcurraghhu@house.gov"},
{"username":"oheisterhv","password":"F2kgGRfx0","email":"gcalverhv@thetimes.co.uk"},
{"username":"cmckiniehw","password":"uzeBvKYFgLft","email":"lzanrehw@baidu.com"},
{"username":"gdevillehx","password":"Z5vi9brDsI","email":"ddeniscohx@cpanel.net"},
{"username":"kkezarhy","password":"QscOGl","email":"sdurranshy@marketwatch.com"},
{"username":"lbelfieldhz","password":"qPe7hW","email":"sdiboldihz@taobao.com"},
{"username":"rcrosei0","password":"X532do6Z8tX","email":"hvahli0@harvard.edu"},
{"username":"mroundingi1","password":"CjxYYyCiG","email":"fhurnelli1@yellowpages.com"},
{"username":"rwerretti2","password":"OgVRhWXi","email":"mhealesi2@loc.gov"},
{"username":"zcharltoni3","password":"U7i0faNcwS","email":"clampeni3@timesonline.co.uk"},
{"username":"nbenfordi4","password":"ExtWKoqj1","email":"meriki4@marriott.com"},
{"username":"ndudmarshi5","password":"yyB7DesCi","email":"ctamburoi5@blinklist.com"},
{"username":"lhockingi6","password":"v2djtb6fEm","email":"bgulleni6@163.com"},
{"username":"rjendruschi7","password":"3ZFrGqv","email":"gpidoni7@vinaora.com"},
{"username":"lgaffneyi8","password":"36LoJcC1UO","email":"vdulwitchi8@sbwire.com"},
{"username":"opriski9","password":"nUMNhzzdrjg","email":"cmcclaryi9@prnewswire.com"},
{"username":"kglazebrookia","password":"CSaw5Fale","email":"lfernihoughia@walmart.com"},
{"username":"bheadingsib","password":"GDqTQhDkA","email":"cwraightib@hao123.com"},
{"username":"wsmothic","password":"DuDbHtHvGoG","email":"hpattonic@nsw.gov.au"},
{"username":"fmanginid","password":"PUcRJ0lL","email":"vcucheyid@buzzfeed.com"},
{"username":"iszymanskiie","password":"8Qh0CA6cE","email":"rcaveie@bizjournals.com"},
{"username":"psheridanif","password":"R4bfyn5XF","email":"nfedorskiif@e-recht24.de"},
{"username":"hivkovicig","password":"d4c6TqQga","email":"aschirachig@acquirethisname.com"},
{"username":"ncovertih","password":"mcA3ea9BEAl","email":"mbickerdickeih@si.edu"},
{"username":"nloudwellii","password":"7JJ6sX","email":"ldruganii@pcworld.com"},
{"username":"imccafferkyij","password":"7g94LytvTKzl","email":"bdowdamij@goo.ne.jp"},
{"username":"dpashleyik","password":"9pBSOmTbaDH","email":"cmeindlik@mozilla.org"},
{"username":"lseakingil","password":"InDKCT2Xz","email":"malchinil@arstechnica.com"},
{"username":"bdessentim","password":"DhRZRs3","email":"bborrettim@acquirethisname.com"},
{"username":"sduffieldin","password":"j5h7TtgZsH","email":"lhunnin@state.gov"},
{"username":"jyakovio","password":"ocQbovuY","email":"bglavinio@nih.gov"},
{"username":"hmielnikip","password":"wYvNU1HZIK","email":"aeggersip@friendfeed.com"},
{"username":"dpardaliq","password":"eRUj17IFGEW","email":"nmarioniq@imgur.com"},
{"username":"bcasettair","password":"wkdZq4TGC","email":"kkisarir@toplist.cz"},
{"username":"amacgallis","password":"zGXNPXz","email":"bdaddsis@netlog.com"},
{"username":"emangeotit","password":"RiX5Nblfz","email":"pbasiliit@ed.gov"},
{"username":"bashmentiu","password":"m1aeQ5hun0","email":"jcorshamiu@soup.io"},
{"username":"cnuddiv","password":"59cjB9TW","email":"igoneauiv@epa.gov"},
{"username":"cdowsettiw","password":"RP7x01U95IWZ","email":"jbaudessoniw@gov.uk"},
{"username":"nphelanix","password":"RcRWdl9ZsR5","email":"ddanksix@sohu.com"},
{"username":"jjoesburyiy","password":"zhG8efz6","email":"bjoubertiy@ycombinator.com"},
{"username":"dhartroppiz","password":"xrZQEEv","email":"bzammettiz@oracle.com"},
{"username":"bsurmeyerj0","password":"0fnDG9L5Pv3p","email":"sbonhanj0@lycos.com"},
{"username":"abradyj1","password":"F7EG7wSb","email":"jweildj1@nymag.com"},
{"username":"eyewdalej2","password":"u1L2RufVljM","email":"dsapsfordej2@weibo.com"},
{"username":"sdealtryj3","password":"5X1zph","email":"gjohanssenj3@tripadvisor.com"},
{"username":"jtravesj4","password":"Ex9i6XhNNMJ","email":"zfillisj4@comcast.net"},
{"username":"cglaisterj5","password":"RtKatj7","email":"cbernardinoj5@huffingtonpost.com"},
{"username":"iheffordej6","password":"lcrJoxImWB","email":"mhulbertj6@icq.com"},
{"username":"tstillertj7","password":"aNjAbBx0T","email":"bchapellej7@goo.ne.jp"},
{"username":"tradinj8","password":"FwqHZ3g","email":"bpesselj8@japanpost.jp"},
{"username":"hburchillj9","password":"wrFKhnNdCfa","email":"osedgemondj9@auda.org.au"},
{"username":"rredihoughja","password":"eUpec6","email":"rirdaleja@ucoz.com"},
{"username":"kbiaggiottijb","password":"2v9YyyoDV","email":"rcoarserjb@sfgate.com"},
{"username":"gclaessensjc","password":"DWxxn0fkz93","email":"rtrevershjc@amazonaws.com"},
{"username":"uhillumjd","password":"GswDsFMuO4","email":"ghansleyjd@mtv.com"},
{"username":"mnellesje","password":"Zi3H6l3b3","email":"cgerattje@vistaprint.com"},
{"username":"sjebbjf","password":"gsvoOXItv2","email":"gfoysterjf@eventbrite.com"},
{"username":"dheinigjg","password":"AHhery","email":"mmcomishjg@tamu.edu"},
{"username":"ahamberstonjh","password":"FiCOkBJDrB4","email":"gdillicatejh@chron.com"},
{"username":"mgartinji","password":"gf4Oan6bQzC","email":"grisebrowji@csmonitor.com"},
{"username":"jbricknalljj","password":"ZXZaGiLU","email":"lashbeejj@jigsy.com"},
{"username":"aenriettojk","password":"B0ta2x3d","email":"cmarriottjk@sitemeter.com"},
{"username":"ggribbenjl","password":"wokLiSN","email":"bbentsonjl@hhs.gov"},
{"username":"rfockejm","password":"pD4YZAe","email":"mabbissjm@netscape.com"},
{"username":"jstaytjn","password":"o4TFsLnwODY","email":"mmuffenjn@altervista.org"},
{"username":"cmattosoffjo","password":"ZjRI63lq","email":"rboshelljo@spotify.com"},
{"username":"nbadenjp","password":"vMzMN9PwuJMA","email":"ldarkinsjp@de.vu"},
{"username":"neadyjq","password":"jFH5KjDUbGE","email":"fciepluchjq@cyberchimps.com"},
{"username":"tsterleyjr","password":"VHVvmjDBucm2","email":"raronoffjr@cpanel.net"},
{"username":"klethbrigjs","password":"4E6li8Cbyx","email":"eceelyjs@pinterest.com"},
{"username":"jdibdenjt","password":"4gj7TIiA","email":"uchristaeasjt@reverbnation.com"},
{"username":"lchaiseju","password":"fNO9AkmoMuWK","email":"hhartfieldju@slideshare.net"},
{"username":"dstollenbergjv","password":"eO7KddayX2e","email":"rfrichleyjv@123-reg.co.uk"},
{"username":"glouisetjw","password":"E1m2K6iqJ8","email":"dsidebothamjw@parallels.com"},
{"username":"tmurcottjx","password":"QqeZFYFOLgo","email":"hfostenjx@sfgate.com"},
{"username":"agarwilljy","password":"XXGEJTiX1uul","email":"gbeardshawjy@bbb.org"},
{"username":"xrainsjz","password":"UpzaVZ","email":"cczajkajz@vistaprint.com"},
{"username":"cdarnbrookk0","password":"d5jhcW","email":"lroomk0@disqus.com"},
{"username":"dpavlishchevk1","password":"hf3Pmc7nNLSi","email":"gdumbellk1@un.org"},
{"username":"ibreslauerk2","password":"FuqAOi8sT","email":"kbartramk2@goo.gl"},
{"username":"mhedlestonek3","password":"WtThJridHsz","email":"pbroughamk3@netlog.com"},
{"username":"cenderwickk4","password":"yF57a7Eogg7j","email":"ablundank4@oakley.com"},
{"username":"walenshevk5","password":"gnm3J1edCzs","email":"jwaythingk5@feedburner.com"},
{"username":"bwellbelovek6","password":"nfYQ6DwZ80z","email":"phaskewk6@uol.com.br"},
{"username":"asimank7","password":"jvQsuuk","email":"cventumk7@ehow.com"},
{"username":"mkillingbackk8","password":"5mqnx0KGe","email":"cmeachk8@businesswire.com"},
{"username":"aeloik9","password":"7Nw3Y97O","email":"ehattiffk9@wiley.com"},
{"username":"dscamadineka","password":"krTE1c","email":"ereidshawka@nationalgeographic.com"},
{"username":"uansillkb","password":"ALYvnVLe","email":"enorawaykb@imdb.com"},
{"username":"hbartzenkc","password":"UXoonprZlri","email":"mkestonkc@vimeo.com"},
{"username":"rkellogkd","password":"LldtF714gVX","email":"lpatriekd@i2i.jp"},
{"username":"awilceke","password":"b171z5LLo2I","email":"ycrouseke@soup.io"},
{"username":"tgoraccikf","password":"V7OT5HBpzysu","email":"eroffeykf@w3.org"},
{"username":"adaethkg","password":"ynZmPfIq","email":"mroncakg@amazon.co.jp"},
{"username":"mdewiskh","password":"ttoUIS","email":"rstockneykh@topsy.com"},
{"username":"cmeadki","password":"J5VLirDivjOK","email":"dyankinki@ibm.com"},
{"username":"pleelekj","password":"GuNrBLM8","email":"kmorrallkj@theguardian.com"},
{"username":"gisakovitchkk","password":"ZokflToMErPT","email":"gsmallacombekk@spiegel.de"},
{"username":"mbazogekl","password":"LSxA9sKWfBT","email":"jeneaskl@state.tx.us"},
{"username":"zmcquilliamkm","password":"WodYANgPd58","email":"celsburykm@uol.com.br"},
{"username":"eandreichikkn","password":"2gUxVrH3","email":"rbogieskn@oakley.com"},
{"username":"vyoellko","password":"jq7ygV","email":"bcapehornko@g.co"},
{"username":"lfayerbrotherkp","password":"jGiZgKp","email":"cstenningskp@fc2.com"},
{"username":"nchittleburghkq","password":"2jZKVISpWKl","email":"jtruelovekq@miibeian.gov.cn"},
{"username":"njoutapaviciuskr","password":"I01cSXS","email":"bboshardkr@ucsd.edu"},
{"username":"lskelhorneks","password":"8n12YL9Kdvc","email":"cfrediks@google.cn"},
{"username":"tweiserkt","password":"JDk0zSS1NtN","email":"abeddonkt@list-manage.com"},
{"username":"ubrabinku","password":"vxrOv4","email":"smeneuxku@1und1.de"},
{"username":"lwhitwhamkv","password":"hgS2pfrJqE9","email":"hcarradicekv@nps.gov"},
{"username":"bseamerkw","password":"VXAIVZ","email":"ccartykw@psu.edu"},
{"username":"abauduinkx","password":"8zRQAnz","email":"akillguskx@people.com.cn"},
{"username":"lwoltonky","password":"Zcn3kG2C9r6k","email":"fbinesteadky@salon.com"},
{"username":"jcocherkz","password":"4x4fM5sRcK","email":"ehalsekz@cbc.ca"},
{"username":"ktaffarellol0","password":"AwHOv8jo7","email":"vrispinel0@dropbox.com"},
{"username":"maleksandrevl1","password":"GGTQMPrL50DF","email":"aarentl1@amazon.com"},
{"username":"sgoodbairnl2","password":"VUA6IDI","email":"lhousbyl2@rambler.ru"},
{"username":"rgammadel3","password":"RqqJOhZzHMm","email":"fbarnbyl3@japanpost.jp"},
{"username":"gporchl4","password":"p2zhdzC3","email":"barnol4@prweb.com"},
{"username":"mplowrightl5","password":"PzbIE9AF3b","email":"lbirtwelll5@ovh.net"},
{"username":"pashmolel6","password":"kOy6CfMa5sZ","email":"kgoggeyl6@drupal.org"},
{"username":"sscoughl7","password":"WBxxufx","email":"iharrapl7@hp.com"},
{"username":"mwestfrimleyl8","password":"f6HVp7w7x","email":"zmccorkelll8@chron.com"},
{"username":"sengell9","password":"7PIgx5pEBz","email":"aleadbeatterl9@state.gov"},
{"username":"hranshawla","password":"g5c31pzVKiJU","email":"nllywarchla@chronoengine.com"},
{"username":"mmingottilb","password":"RLGG9fnHq","email":"kjankowskilb@ow.ly"},
{"username":"dsmithendlc","password":"WgXPnQYzap","email":"hbleazardlc@twitter.com"},
{"username":"khardenld","password":"Htq2XHmSXoNs","email":"esirmonld@pcworld.com"},
{"username":"bsnasdellle","password":"ElhcAK","email":"evannerle@last.fm"},
{"username":"cracklf","password":"vgJO1joiWY9","email":"oguionlf@ebay.co.uk"},
{"username":"cpursglovelg","password":"BcreX05","email":"fdybaldlg@netvibes.com"},
{"username":"dgrangerlh","password":"EpLGpQPN","email":"mavrahamianlh@oakley.com"},
{"username":"mlemarchandli","password":"zxgRSn","email":"mdjurisicli@cornell.edu"},
{"username":"groxburghlj","password":"2DcUma","email":"btregentlj@skype.com"},
{"username":"adundredgelk","password":"hhwy2Eqy2","email":"bvoadenlk@utexas.edu"},
{"username":"gdarthll","password":"d6fTgn","email":"cfaivrell@wsj.com"},
{"username":"wbedfordlm","password":"0BED3PuFAAw","email":"csackettlm@comsenz.com"},
{"username":"mblaisln","password":"oj6JWG","email":"npatricheln@pbs.org"},
{"username":"msheatherlo","password":"ky2zi3eOtS","email":"slowethlo@opera.com"},
{"username":"vrolfslp","password":"YJVPJX1I","email":"fblampeylp@wix.com"},
{"username":"egammonlq","password":"OEc3DhekBEeJ","email":"dbradmanlq@qq.com"},
{"username":"wtarplylr","password":"zzefUY9pCg81","email":"eemmanuelelr@mashable.com"},
{"username":"titzchakyls","password":"uDhbSarKNQ","email":"ebraywoodls@msn.com"},
{"username":"wgallicolt","password":"4Q31tOmZ","email":"fghiraldilt@wikipedia.org"},
{"username":"jpashbalu","password":"x12GKnB","email":"jmccroarylu@odnoklassniki.ru"},
{"username":"sdowbekinlv","password":"W6267a1a","email":"agarmslv@sphinn.com"},
{"username":"ahartzogslw","password":"vYlXRD6vrrC","email":"fklimeslw@tuttocitta.it"},
{"username":"raikenlx","password":"WMj5Gq6vKyK","email":"fpoelx@ameblo.jp"},
{"username":"ahearnely","password":"ENLdthJTbx","email":"sskokoely@patch.com"},
{"username":"lcarracklz","password":"gWcsikIf80O","email":"bkrellelz@about.com"},
{"username":"hrobensm0","password":"Rpl1QRnN","email":"lrobothamm0@ebay.com"},
{"username":"gduchantm1","password":"tFiaDLGU","email":"cgarzam1@mozilla.com"},
{"username":"eheddenm2","password":"tucmWzsfPku","email":"pbrandesm2@w3.org"},
{"username":"fmaypesm3","password":"N02AdlN4f7j7","email":"ddunstanm3@clickbank.net"},
{"username":"lscarsbrookem4","password":"FLnJV8G","email":"khutchesonm4@nature.com"},
{"username":"ddenisardm5","password":"WGjXcpl","email":"lhaineym5@ebay.co.uk"},
{"username":"kbennym6","password":"TeE7WeBB6","email":"mgrzegoreckim6@nih.gov"},
{"username":"mbirdallm7","password":"jiEUEk","email":"mdooneym7@state.gov"},
{"username":"cdraperm8","password":"tPRMrs","email":"apignym8@google.ca"},
{"username":"bpooleym9","password":"bW0k9BC7fhqX","email":"wmiddlemassm9@over-blog.com"},
{"username":"awaldenma","password":"qhIzrSWYty","email":"mcolliverma@baidu.com"},
{"username":"gvanmb","password":"JViXk5VLkG","email":"mboumphreymb@naver.com"},
{"username":"hrapomc","password":"pmsYaCPK7","email":"stackmc@mayoclinic.com"},
{"username":"abarwickmd","password":"zBtReVQ0C","email":"sgillbardmd@i2i.jp"},
{"username":"dboykettme","password":"5zbdgnJdh","email":"abernadonme@earthlink.net"},
{"username":"gpetrenmf","password":"UjGdmHLUVwEf","email":"sbilfootmf@google.co.jp"},
{"username":"spappimg","password":"eyLktq4","email":"fhandscombemg@soundcloud.com"},
{"username":"vtompkinsonmh","password":"WtmfG6vBT","email":"dparkmh@tamu.edu"},
{"username":"hongmi","password":"qBgAxhpcgn","email":"cdutchburnmi@shinystat.com"},
{"username":"bwoolismj","password":"HyEl4g","email":"vkellochmj@flickr.com"},
{"username":"hboynemk","password":"R53NU8rYf","email":"cwhitloemk@cbslocal.com"},
{"username":"bffrenchml","password":"oek5STg","email":"mpagenml@youtube.com"},
{"username":"bglassupmm","password":"3CCHqoPl5A","email":"ehellmermm@ning.com"},
{"username":"lcrakemn","password":"87tRNDw","email":"fvanyardmn@qq.com"},
{"username":"nreastmo","password":"uFUKsC4","email":"dgounodmo@zimbio.com"},
{"username":"swimpennymp","password":"cIcZw1jANP9","email":"jcalemp@google.co.uk"},
{"username":"ctradewellmq","password":"7naUThu","email":"ilainmq@ca.gov"},
{"username":"ghardwaymr","password":"pj1nIkBD","email":"atelfordmr@myspace.com"},
{"username":"gtroodms","password":"B3PBiH98RC","email":"dfernsms@elegantthemes.com"},
{"username":"hlandreanmt","password":"2WA8Vuy8To","email":"btoffolonimt@adobe.com"},
{"username":"mburnellmu","password":"vICvid","email":"vedsonmu@histats.com"},
{"username":"zarchambaultmv","password":"5OHpqXoM1M","email":"ejardinmv@omniture.com"},
{"username":"nlownmw","password":"Z9fBhqenPq","email":"epeakermw@uol.com.br"},
{"username":"hradbournmx","password":"EdR1GEX8JC","email":"mrobeletmx@ucoz.com"},
{"username":"lsellsmy","password":"2hZdWh9c1Bg","email":"cmellanbymy@vkontakte.ru"},
{"username":"apextonmz","password":"s83fIso8tMWV","email":"fgoldstonmz@princeton.edu"},
{"username":"bhullockn0","password":"5LliQRq7M","email":"kmccrorien0@infoseek.co.jp"},
{"username":"oheminsleyn1","password":"Fttl3Yt","email":"mkurthn1@seesaa.net"},
{"username":"paudibertn2","password":"ccAdZs5Kmh","email":"sgowenn2@seattletimes.com"},
{"username":"bwrankmoren3","password":"JixwMmS8y6","email":"mtwycrossn3@hhs.gov"},
{"username":"mgawken4","password":"72t8DRr6NVb","email":"dbouttelln4@google.co.uk"},
{"username":"aleahn5","password":"fjNYDw0K4zM","email":"lthomeln5@blogs.com"},
{"username":"akimblingn6","password":"spSWyVBXvBB","email":"obrownn6@gnu.org"},
{"username":"dlefeavern7","password":"4VgEa3tE","email":"cpibornn7@omniture.com"},
{"username":"clavendern8","password":"ZwQ2hFDtjBW","email":"iferrierin8@home.pl"},
{"username":"gpolinon9","password":"codO5dlhpJIB","email":"ecordreyn9@hexun.com"},
{"username":"rburnesna","password":"O6SuhyQHc","email":"wmillsapna@mtv.com"},
{"username":"nmillsomnb","password":"crsdTCqBxIe","email":"lklainmannb@jigsy.com"},
{"username":"cinfantenc","password":"F4LlsB","email":"ddudinnc@va.gov"},
{"username":"npatisnd","password":"wUxeh94VYdnu","email":"knehlsennd@hostgator.com"},
{"username":"rrabsonne","password":"XHJICLZlYIvl","email":"dgrassickne@google.cn"},
{"username":"mroadsnf","password":"JKMnbl","email":"tblaineynf@dell.com"},
{"username":"lraddishng","password":"v9ociXz","email":"apretong@wikia.com"},
{"username":"bcorradeschinh","password":"SEmv2ju","email":"mwendovernh@abc.net.au"},
{"username":"lzorzenonini","password":"3Dj53TtTaSLk","email":"ntomasikni@jigsy.com"},
{"username":"abewleynj","password":"6xeRu9oz59","email":"bvallownj@auda.org.au"},
{"username":"tpeasemannk","password":"sk5Ouc7yslK","email":"fgrzelczaknk@godaddy.com"},
{"username":"jbrahannl","password":"9kiOPttoh","email":"kgraffhamnl@economist.com"},
{"username":"ttitheringtonnm","password":"SNX5Blib","email":"cwadenm@amazon.co.uk"},
{"username":"mebbersnn","password":"iroOx3dv","email":"wbodkernn@arstechnica.com"},
{"username":"oforteno","password":"P2xvt6rSz","email":"dteresseno@posterous.com"},
{"username":"swhyffennp","password":"VaoaF8faJg2","email":"vdanknp@phoca.cz"},
{"username":"ngatrillnq","password":"0uIfap8","email":"lantcliffenq@pinterest.com"},
{"username":"maugustusnr","password":"ilttSkk5THV","email":"avearnalsnr@behance.net"},
{"username":"dwarrattns","password":"4ry0Cx2","email":"mhoogendorpns@jiathis.com"},
{"username":"egratlandnt","password":"HYusNOodqJzK","email":"dbiasiolint@cpanel.net"},
{"username":"hstychenu","password":"chqBlrC","email":"ksennernu@nba.com"},
{"username":"dodcroftnv","password":"vI5pp5","email":"ckemenv@mozilla.org"},
{"username":"givannw","password":"tg1mMS","email":"mhewesnw@engadget.com"},
{"username":"ohayternx","password":"a4ieCJ6Vor","email":"kkeelingnx@squarespace.com"},
{"username":"emcsporonny","password":"PyHxUXDvE91N","email":"okennewayny@dedecms.com"},
{"username":"lhirtznz","password":"UT65Ze","email":"dgriswaitenz@wired.com"},
{"username":"ibourdiceo0","password":"ZyPA1SfJ","email":"bmcgloughlino0@go.com"},
{"username":"rcarmelo1","password":"eFNnJJhzI","email":"cbacchuso1@meetup.com"},
{"username":"spascheko2","password":"yLvCy0Q5gTCH","email":"nbiasiolio2@sun.com"},
{"username":"kwhoolehano3","password":"tOJHqp2UaY9","email":"ajilletto3@fotki.com"},
{"username":"ltreharneo4","password":"yVO3iCsTh","email":"rrobertoo4@baidu.com"},
{"username":"dlittlechildo5","password":"hmVKZmz","email":"ghanneno5@businesswire.com"},
{"username":"fgadsbyo6","password":"FNdzBHM","email":"tbasindaleo6@youtube.com"},
{"username":"lbirchnero7","password":"pQoNy1","email":"llomazo7@ed.gov"},
{"username":"cballinghallo8","password":"hCcqGWMIRc","email":"sandrionio8@edublogs.org"},
{"username":"nfranceschio9","password":"bfhaoyRYL8","email":"kaxtonneo9@redcross.org"},
{"username":"demonsoa","password":"TlurLXNxmGD","email":"mbanhamoa@cbslocal.com"},
{"username":"ncloonanob","password":"ffUj2Uo","email":"lrammellob@wikipedia.org"},
{"username":"cobeeoc","password":"7AL38goEB","email":"caxtensoc@mapy.cz"},
{"username":"lmcmennumod","password":"13Y62JCOOci","email":"gchretienod@mac.com"},
{"username":"lkarimoe","password":"QT6lIpPWvTk","email":"wdurbanoe@blog.com"},
{"username":"gchapelhowof","password":"1eH9z8livr","email":"cheymesof@princeton.edu"},
{"username":"gbowldog","password":"0HAAQO","email":"cyushkinog@go.com"},
{"username":"hbeastonoh","password":"diNRvqLoUW2n","email":"ajanuszewiczoh@craigslist.org"},
{"username":"dtallmanoi","password":"aBK4czMX8Qmo","email":"mbrounfieldoi@timesonline.co.uk"},
{"username":"scolcomboj","password":"nWZ3Nn","email":"ahendersonoj@mozilla.org"},
{"username":"grevellok","password":"kXTnI3","email":"kstayteok@dot.gov"},
{"username":"acollacombeol","password":"HLmaxpfNEHFU","email":"mkeeseol@digg.com"},
{"username":"glenzom","password":"7jYqsSwGR","email":"gstollwerkom@yellowbook.com"},
{"username":"rstrowtheron","password":"iKWJlHZIg","email":"edobbynon@phpbb.com"},
{"username":"tthwaiteoo","password":"Ao1B7eeZXg","email":"lbradfordoo@1und1.de"},
{"username":"dhounsomop","password":"szYu1LeIlp","email":"pcanaop@nyu.edu"},
{"username":"dgallonoq","password":"4VHQ0se4f9q","email":"cgalvinoq@washingtonpost.com"},
{"username":"egiffordor","password":"9sAkVlYrB","email":"mgoodbairnor@so-net.ne.jp"},
{"username":"dfeareyos","password":"Aud5xLmR","email":"mdasos@narod.ru"},
{"username":"codoghestyot","password":"MtvEi22kRx2","email":"amassyot@reuters.com"},
{"username":"mcainesou","password":"I9YxHf1YyE","email":"mmaccafferyou@furl.net"},
{"username":"llauov","password":"nIWQDRx","email":"llentonov@cmu.edu"},
{"username":"tsexonow","password":"1lSIMyMu2f8p","email":"amortelow@discuz.net"},
{"username":"eorpyneox","password":"8i2lSAZNo","email":"vkeelinox@upenn.edu"},
{"username":"mcanlandoy","password":"RtPy1URY","email":"ldenyukhinoy@google.de"},
{"username":"spenvarneoz","password":"LFoDdAXcc9yk","email":"sarmsteadoz@google.co.uk"},
{"username":"nnegrop0","password":"BXAohsjOn","email":"slangfieldp0@dropbox.com"},
{"username":"juddenp1","password":"fxzaAwq","email":"rbenjafieldp1@so-net.ne.jp"},
{"username":"dwaterhowsep2","password":"RNPMMGZ","email":"cdoddridgep2@technorati.com"},
{"username":"eberthp3","password":"CZTMJkddZOqL","email":"wrudhamp3@whitehouse.gov"},
{"username":"hlamiep4","password":"dmTPqs8ikaG","email":"rpaviep4@auda.org.au"},
{"username":"lsturgeonp5","password":"WjdnxX7mcC","email":"leastp5@archive.org"},
{"username":"ndeguerrep6","password":"Yc3HYpvX","email":"gyarnellp6@posterous.com"},
{"username":"ntomikp7","password":"JU1V8hE883c3","email":"dmeneop7@yandex.ru"},
{"username":"cvondruskap8","password":"UUokKgoAS","email":"cgemlbettp8@privacy.gov.au"},
{"username":"jfucherp9","password":"42F7aCrI23","email":"lswindlehurstp9@statcounter.com"},
{"username":"ochisolmpa","password":"WIKddvqw","email":"sdrescherpa@answers.com"},
{"username":"edorrellpb","password":"k4rQhf4dTN9","email":"wnorkerpb@instagram.com"},
{"username":"bghirigoripc","password":"RXbgBIpaW","email":"dgoundsypc@bloomberg.com"},
{"username":"vskevingtonpd","password":"hGVtynmt","email":"mmargerisonpd@webmd.com"},
{"username":"fzuppape","password":"7E4a4HsN","email":"gbrandinpe@marketwatch.com"},
{"username":"abattanypf","password":"lPITh0","email":"pwestonpf@reference.com"},
{"username":"pnaeruppg","password":"ms5kFbE3","email":"smartynkapg@oaic.gov.au"},
{"username":"bizkoviciph","password":"KAIDHSBg7EF","email":"colerenshawph@wikimedia.org"},
{"username":"abericpi","password":"Q6CUTb","email":"wteasdalemarkiepi@europa.eu"},
{"username":"mmarchipj","password":"HGIZ74ZVv","email":"rdewanpj@google.nl"},
{"username":"tgrattanpk","password":"0r3jrRlyZJK","email":"cwisniowskipk@tuttocitta.it"},
{"username":"meaddypl","password":"pCVPHY","email":"trosemanpl@lycos.com"},
{"username":"udayespm","password":"0pwJqD","email":"abrownscombepm@dropbox.com"},
{"username":"kffordepn","password":"pcB2mvEohjR","email":"bderkespn@reuters.com"},
{"username":"ehazelhurstpo","password":"cm0j0yeCT","email":"khampepo@mapy.cz"},
{"username":"eduganpp","password":"mAwTRpv1","email":"zkerswillpp@walmart.com"},
{"username":"gberthelmotpq","password":"nn7MN7","email":"elilleycroppq@booking.com"},
{"username":"jjearypr","password":"3lIvCj8rk","email":"idisleepr@miitbeian.gov.cn"},
{"username":"knystromps","password":"uWyZUSZCMA","email":"tpolackps@apple.com"},
{"username":"alindermannpt","password":"iK6J7S7jDT","email":"egillumpt@fda.gov"},
{"username":"rearppu","password":"33hjSuWw52","email":"efranssenpu@google.nl"},
{"username":"avoaspv","password":"3AVU374Mf","email":"kleppingtonpv@netscape.com"},
{"username":"sdanaherpw","password":"xINImLM8oGAC","email":"gstoddardpw@addtoany.com"},
{"username":"akennerknechtpx","password":"6p9HCH","email":"rhamilpx@bbc.co.uk"},
{"username":"mmcpartlinpy","password":"u0XoUQ1S5","email":"ahampsonpy@ehow.com"},
{"username":"creadheadpz","password":"4IfTXhQ","email":"gricciopz@php.net"},
{"username":"lecclestonq0","password":"UYo5f7crPZ","email":"rflugerq0@gov.uk"},
{"username":"akahaneq1","password":"2FIx5wweHql","email":"eortasq1@smh.com.au"},
{"username":"pivashnikovq2","password":"O3Vg8rCsiekm","email":"alefeuvreq2@redcross.org"},
{"username":"mbarrq3","password":"qSR44wTV36","email":"ikeizmanq3@usda.gov"},
{"username":"vreddlesdenq4","password":"ZlIpBKI","email":"kmcbainq4@sbwire.com"},
{"username":"ebearcroftq5","password":"pkHB7mG9epd","email":"adolemanq5@t.co"},
{"username":"msawdonq6","password":"F6Pr08E6","email":"lprykeq6@pen.io"},
{"username":"mpauleq7","password":"WUnd135Tp","email":"dstolleryq7@typepad.com"},
{"username":"gvasyukhnovq8","password":"YO4VVw","email":"gdoogoodq8@bing.com"},
{"username":"sdownesq9","password":"th1wjlaG3p","email":"athurleyq9@techcrunch.com"},
{"username":"rgrunguerqa","password":"n4lzYR3mHpOL","email":"jbrockestqa@technorati.com"},
{"username":"iburnieqb","password":"5JMvvzA93Tz","email":"cminichilloqb@com.com"},
{"username":"jseylerqc","password":"VvxyKiz","email":"rgunsonqc@hp.com"},
{"username":"achomiszewskiqd","password":"jeYJOXwBJK","email":"jthirskqd@slashdot.org"},
{"username":"vdavernqe","password":"egkB2R5","email":"cbrillemanqe@bloglines.com"},
{"username":"scommingsqf","password":"0KBMwhH8B7","email":"mlongdonqf@baidu.com"},
{"username":"cparkeyqg","password":"rJEY0fph","email":"showbrookqg@epa.gov"},
{"username":"hhickissonqh","password":"9kdNVLiEpt","email":"cshoweringqh@slashdot.org"},
{"username":"opeadqi","password":"e2jqWZ8","email":"sscarrottqi@privacy.gov.au"},
{"username":"swoollinqj","password":"kwIJO01","email":"psolomonidesqj@soup.io"},
{"username":"rhirschmannqk","password":"ga6f2t3E","email":"gkarusqk@github.com"},
{"username":"tparfreyql","password":"K7CZXO6Qwl","email":"ntownsendql@youtube.com"},
{"username":"uiddonsqm","password":"nBUOmWOoabH1","email":"dsimkovitzqm@wisc.edu"},
{"username":"mgomezqn","password":"HMJKxf","email":"wbattesonqn@example.com"},
{"username":"rcordeiroqo","password":"aewJMhQ","email":"wheadyqo@4shared.com"},
{"username":"bcatchersideqp","password":"qk9Zi9e89mIR","email":"rmarshalqp@dmoz.org"},
{"username":"sheinritzqq","password":"4Vy9x0aLw","email":"llohdeqq@epa.gov"},
{"username":"adelgatyqr","password":"FTDg0lbrS","email":"klochranqr@github.com"},
{"username":"bhelstripqs","password":"9boc0lGHZ","email":"agillfillanqs@cdc.gov"},
{"username":"rwhitesideqt","password":"hL71b4","email":"cgiffordqt@bluehost.com"},
{"username":"smcleanqu","password":"r0E980HWU","email":"kbummfreyqu@seattletimes.com"},
{"username":"charvardqv","password":"sDvlAy2Kaoh","email":"jnairnqv@goo.gl"},
{"username":"vhirjakqw","password":"Bv0gySa4xTOM","email":"gpaffordqw@time.com"},
{"username":"kforstallqx","password":"CplvlzZ","email":"acastletonqx@deviantart.com"},
{"username":"mheathcoteqy","password":"oky7JWmJwnmp","email":"mdomninqy@webnode.com"},
{"username":"zgrigorievqz","password":"VR6k1gcUCMkV","email":"cpawlynqz@opensource.org"},
{"username":"wkeatchr0","password":"wyCkWz6R6yHC","email":"ebreemr0@plala.or.jp"},
{"username":"cheersr1","password":"Q9hck2","email":"cstanlockr1@amazon.com"},
{"username":"gpledgerr2","password":"KulKD46a","email":"lconradr2@mtv.com"},
{"username":"kpigdenr3","password":"3TWjC9","email":"dkeaner3@acquirethisname.com"},
{"username":"avassarr4","password":"BW1fTeJQd","email":"lbartholatr4@psu.edu"},
{"username":"lkinetonr5","password":"AwomotN","email":"kmilleryr5@walmart.com"},
{"username":"cmarchbankr6","password":"K8LaZi","email":"agoutr6@pinterest.com"},
{"username":"tmcillroyr7","password":"qJgbXOT1fBwu","email":"lclewlower7@eepurl.com"},
{"username":"ltempletonr8","password":"NXYA7YDzG","email":"ajirucar8@people.com.cn"},
{"username":"tbracknallr9","password":"7w3FwKJLh","email":"gfordr9@examiner.com"},
{"username":"mvintra","password":"6ICGjd","email":"sroonyra@sitemeter.com"},
{"username":"ahedditchrb","password":"IH2taQuLRaj4","email":"oburnyeatrb@blogger.com"},
{"username":"cjoulrc","password":"02xRsq","email":"akinetonrc@squidoo.com"},
{"username":"smccloshrd","password":"Gc2EPoLOlQz","email":"fsantorerd@japanpost.jp"},
{"username":"jmitchensonre","password":"uoyn57R0y","email":"tborgnere@oracle.com"},
{"username":"blivickrf","password":"8vfiHX3f7Z","email":"nfellenorrf@sitemeter.com"},
{"username":"lmorphetrg","password":"ZKRzvSLS","email":"gcoultishrg@w3.org"},
{"username":"mfeaseyrh","password":"rI9bc048MEzB","email":"kplattrh@google.com.br"},
{"username":"mpontri","password":"Peh7vr","email":"bpostlewhiteri@jigsy.com"},
{"username":"mnorreerj","password":"tx83SurkjZoQ","email":"cstoodalerj@usnews.com"},
{"username":"aocaheyrk","password":"Z2XyIZSk","email":"emullallyrk@stanford.edu"},
{"username":"ecramprl","password":"NzmnOKb","email":"lcarolirl@skyrock.com"},
{"username":"ihemmingwayrm","password":"i3yQFJ","email":"ccluttonrm@prlog.org"},
{"username":"ltayntonrn","password":"KUlSdX8tPMy","email":"nyearnrn@blogtalkradio.com"},
{"username":"dmariaultro","password":"VXaRn6i","email":"cdomelawro@fotki.com"},
{"username":"lmeffinrp","password":"5TKmQiJJ","email":"bousleyrp@europa.eu"},
{"username":"tknowlesrq","password":"NiIzyczKY","email":"mradbornerq@ca.gov"},
{"username":"jlukesrr","password":"32ZhWV","email":"avassmanrr@live.com"}]